{"overdue":"4218","due_today":"9372","due_3days":"13667","due_10days":"13810","safe":"2109","total_active":15919,"by_fleet":{"737":2543,"737MAX":507,"767":560,"777":1129,"777F":584,"787":5487,"Airbus":3650,"Q400":1459},"by_fleet_aircraft":{"737":{"ET-ALM":61,"ET-ALN":255,"ET-APL":60,"ET-APM":240,"ET-APO":60,"ET-AQN":90,"ET-AQO":77,"ET-AQP":75,"ET-AQQ":69,"ET-ASJ":43,"ET-AVX":31,"ET-AWC":38,"ET-AWR":69,"ET-AWS":29,"ET-AXI":332,"ET-AXO":224,"ET-AYL":19,"ET-AYP":18,"ET-AYU":189,"ET-AZY":158,"ET-AZZ":152,"ET-BAG":112,"ET-BAH":106,"ET-BBR":27,"ET-BCF":9},"737MAX":{"ET-AVI":35,"ET-AVK":42,"ET-AVL":27,"ET-AVM":53,"ET-AWF":21,"ET-AWG":25,"ET-AWH":47,"ET-AWI":34,"ET-AWJ":29,"ET-AWK":17,"ET-AXG":26,"ET-AZA":22,"ET-AZO":47,"ET-BAI":14,"ET-BAJ":6,"ET-BAK":6,"ET-BAL":13,"ET-BAM":4,"ET-BAN":9,"ET-BAO":10,"ET-BBA":14,"ET-BBC":6},"767":{"3C-MAG":72,"ET-ALO":249,"ET-ALP":212,"ET-BBE":10,"ET-BBF":17},"777":{"ET-ANN":113,"ET-ANO":103,"ET-ANP":80,"ET-ANQ":99,"ET-ANR":121,"ET-APX":109,"ET-APY":109,"ET-AQL":139,"ET-ASK":127,"ET-ASL":103,"ET-BBG":26},"777F":{"ET-APS":70,"ET-APU":83,"ET-ARI":89,"ET-ARJ":84,"ET-ARK":44,"ET-AVN":64,"ET-AVQ":38,"ET-AVT":51,"ET-AWE":31,"ET-BAA":13,"ET-BAB":10,"ET-BAC":7},"787":{"ET-AOO":236,"ET-AOP":253,"ET-AOQ":361,"ET-AOR":309,"ET-AOS":350,"ET-AOT":177,"ET-AOU":213,"ET-AOV":201,"ET-ARE":192,"ET-ARF":215,"ET-ASG":145,"ET-ASH":214,"ET-ASI":150,"ET-ATG":177,"ET-ATH":97,"ET-ATI":136,"ET-ATJ":149,"ET-ATK":190,"ET-ATL":500,"ET-AUO":192,"ET-AUP":131,"ET-AUQ":135,"ET-AUR":140,"ET-AXK":127,"ET-AXL":115,"ET-AXS":141,"ET-AXT":73,"ET-AYC":105,"ET-AYD":61,"ET-BCC":2},"Airbus":{"ET-ATQ":260,"ET-ATR":333,"ET-ATY":268,"ET-AUA":294,"ET-AUB":271,"ET-AUC":208,"ET-AVB":180,"ET-AVC":105,"ET-AVD":222,"ET-AVE":170,"ET-AWM":150,"ET-AWN":143,"ET-AWO":115,"ET-AWP":229,"ET-AYA":94,"ET-AYB":106,"ET-AYM":110,"ET-AYN":94,"ET-AZI":48,"ET-AZN":63,"ET-BAW":46,"ET-BAX":42,"ET-BAY":43,"ET-BAZ":21,"ET-BCD":18,"ET-BCE":17},"Q400":{"9J-ZAW":100,"ET-ANI":38,"ET-ANJ":149,"ET-ANK":123,"ET-ANL":34,"ET-ANV":55,"ET-ANX":61,"ET-AQB":93,"ET-AQD":34,"ET-AQE":59,"ET-AQF":50,"ET-ARL":68,"ET-ARM":28,"ET-ARN":118,"ET-ASA":27,"ET-AUD":45,"ET-AUE":62,"ET-AVA":32,"ET-AVH":33,"ET-AVR":41,"ET-AXE":17,"ET-AXF":28,"ET-AXP":22,"ET-AXW":44,"ET-AXX":12,"ET-AXY":24,"ET-AXZ":16,"ET-AYF":9,"ET-AYG":26,"ET-AYH":11}},"by_time_limit_source":{"AOG":40,"CDL":272,"CDL-WND":479,"MEL":476,"MINOR":4,"MINR-WD":809,"MINR-WND":2297,"NEFMEL":3325,"TLI":2292,"UNKNOWN":5925},"by_fleet_time_limit_source":{"737":{"AOG":18,"CDL":6,"CDL-WND":30,"MEL":53,"MINOR":1,"MINR-WD":78,"MINR-WND":181,"NEFMEL":430,"TLI":146,"UNKNOWN":1600},"737MAX":{"CDL":16,"CDL-WND":8,"MEL":22,"MINR-WD":77,"MINR-WND":45,"NEFMEL":198,"TLI":58,"UNKNOWN":83},"767":{"AOG":1,"CDL":18,"CDL-WND":12,"MEL":28,"MINOR":2,"MINR-WD":11,"MINR-WND":74,"NEFMEL":90,"TLI":136,"UNKNOWN":188},"777":{"AOG":1,"CDL":8,"CDL-WND":21,"MEL":60,"MINR-WD":44,"MINR-WND":88,"NEFMEL":250,"TLI":360,"UNKNOWN":297},"777F":{"AOG":1,"CDL":10,"CDL-WND":11,"MEL":66,"MINR-WD":39,"MINR-WND":67,"NEFMEL":69,"TLI":159,"UNKNOWN":162},"787":{"AOG":3,"CDL":83,"CDL-WND":185,"MEL":134,"MINOR":1,"MINR-WD":240,"MINR-WND":982,"NEFMEL":1211,"TLI":682,"UNKNOWN":1966},"Airbus":{"AOG":4,"CDL":98,"CDL-WND":148,"MEL":101,"MINR-WD":254,"MINR-WND":451,"NEFMEL":1016,"TLI":625,"UNKNOWN":953},"Q400":{"AOG":12,"CDL":33,"CDL-WND":64,"MEL":12,"MINR-WD":66,"MINR-WND":409,"NEFMEL":61,"TLI":126,"UNKNOWN":676}},"by_mel_category":{"Unknown":8794,"CDL":344,"MEL A":72,"MEL B":56,"MEL C":525,"MEL D":442,"NEFMEL B":177,"NEFMEL C":295,"NEFMEL D":2885,"OTHER":323,"TLI":7,"TLI-18M":137,"TLI-6M":118,"TLI-90D":1487,"TLI-ENG":257},"by_fleet_mel_category":{"737":{"Unknown":1836,"CDL":16,"MEL A":2,"MEL B":8,"MEL C":48,"MEL D":57,"NEFMEL B":12,"NEFMEL C":25,"NEFMEL D":390,"OTHER":36,"TLI-18M":15,"TLI-6M":9,"TLI-90D":55,"TLI-ENG":34},"737MAX":{"Unknown":138,"CDL":18,"MEL B":5,"MEL C":22,"MEL D":37,"NEFMEL B":12,"NEFMEL C":27,"NEFMEL D":188,"OTHER":20,"TLI-18M":4,"TLI-6M":2,"TLI-90D":12,"TLI-ENG":22},"767":{"Unknown":285,"CDL":18,"MEL A":2,"MEL B":2,"MEL C":28,"MEL D":25,"NEFMEL B":4,"NEFMEL C":8,"NEFMEL D":72,"OTHER":5,"TLI":1,"TLI-18M":3,"TLI-6M":7,"TLI-90D":98,"TLI-ENG":2},"777":{"Unknown":413,"CDL":14,"MEL A":7,"MEL B":7,"MEL C":59,"MEL D":49,"NEFMEL B":9,"NEFMEL C":44,"NEFMEL D":184,"OTHER":26,"TLI":1,"TLI-18M":18,"TLI-6M":10,"TLI-90D":265,"TLI-ENG":23},"777F":{"Unknown":243,"CDL":14,"MEL A":8,"MEL B":3,"MEL C":66,"MEL D":38,"NEFMEL C":8,"NEFMEL D":66,"OTHER":16,"TLI-18M":7,"TLI-6M":5,"TLI-90D":86,"TLI-ENG":24},"787":{"Unknown":3144,"CDL":89,"MEL A":36,"MEL B":11,"MEL C":187,"MEL D":106,"NEFMEL B":66,"NEFMEL C":76,"NEFMEL D":1076,"OTHER":75,"TLI":3,"TLI-18M":44,"TLI-6M":50,"TLI-90D":418,"TLI-ENG":106},"Airbus":{"Unknown":1572,"CDL":137,"MEL A":8,"MEL B":13,"MEL C":87,"MEL D":101,"NEFMEL B":71,"NEFMEL C":101,"NEFMEL D":863,"OTHER":110,"TLI":1,"TLI-18M":30,"TLI-6M":23,"TLI-90D":507,"TLI-ENG":26},"Q400":{"Unknown":1163,"CDL":38,"MEL A":9,"MEL B":7,"MEL C":28,"MEL D":29,"NEFMEL B":3,"NEFMEL C":6,"NEFMEL D":46,"OTHER":35,"TLI":1,"TLI-18M":16,"TLI-6M":12,"TLI-90D":46,"TLI-ENG":20}},"by_ata_seq":{"Unknown":259,"05":28,"05 (1.1)":21,"05-00":223,"05-00 (1.1.1)":53,"05-00-00":24,"05-2 (1.1.1)":23,"05-21 (1.1.1.1)":16,"05-21-90 (1.1.1.1.1)":1,"05-22 (1.1.1.1)":12,"05-23 (1.1.1.1)":1,"05-24 (1.1.1.1)":3,"05-25 (1.1.1.1)":19,"05-28 (1.1.1.1)":4,"05-41":8,"05-41 (1.1.1)":29,"05-41-00":89,"05-42":1,"05-42 (1.1.1)":10,"05-5 (1.1.1)":103,"05-50":3,"05-51":2,"05-51 (1.1.1)":2,"05-51-00":2,"05-55 (1.1.1)":2,"06":23,"06 (1.1)":2,"06-00":44,"06-10":24,"06-10 (1.1.1)":17,"06-10-00":9,"06-21 (1.1.1)":1,"06-24-00":1,"06-41-00":2,"06-42":3,"06-43 (1.1.1)":1,"06-43-00":3,"06-44-00":4,"08-00":1,"09-11":1,"10":1,"10 (1.1)":2,"10-00":4,"11":44,"11 (1.1)":80,"11-00":114,"11-00 (1.1)":2,"11-20":2,"11-20 (1.1.1)":1,"11-21":3,"11-21-00":44,"11-22":14,"11-23":7,"11-23 (1.1.1)":9,"11-23-00":16,"11-24":4,"11-24 (1.1.1)":1,"11-24-00":1,"11-25":5,"11-25 (1.1.1)":1,"11-25-00":11,"11-26 (1.1.1)":1,"11-30":4,"11-30 (1.1.1)":1,"11-31":1,"11-31 (1.1.1)":31,"11-31-00":3,"11-32":3,"11-32-00":7,"11-34 (1.1.1)":18,"11-35":1,"11-36 (1.1.1)":4,"11-37":5,"11-37-00":9,"11-38":2,"12":4,"12 (1.1)":4,"12-0 (1.1.1)":1,"12-00":29,"12-12":1,"12-13-00":4,"12-15":2,"12-15-00":2,"12-21 (1.1.1)":2,"12-21-00":8,"12-3 (1.1.1)":1,"20":7,"20 (1.1)":12,"20-00":28,"20-1 (1.1.1)":2,"20-10":1,"20-10-00":2,"20-30-00":1,"20-40":1,"20-41-00":1,"20-55 (1.1.1.1)":1,"20-60":3,"20-60 (1.1.1)":2,"20-60-00":1,"21":40,"21 (1.1)":5,"21-00":107,"21-00-00":3,"21-2 (1.1.1)":2,"21-20-00":2,"21-21":1,"21-21 (1.1.1.1)":2,"21-21-00":1,"21-21-55 (1.1.1.1.1)":5,"21-22":2,"21-22 (1.1.1.1)":1,"21-22-00":1,"21-22-16-01-010D":1,"21-23":3,"21-23 (1.1.1)":1,"21-23-00":2,"21-24 (1.1.1)":1,"21-24-00":2,"21-24-01-ZA1-005 (1.1)":1,"21-25 (1.1.1)":1,"21-25 (1.1.1.1)":1,"21-25-00":4,"21-26":2,"21-26-00":14,"21-26-01-15-090 (POS1)":1,"21-27":2,"21-27-00":10,"21-27-00-ZA1-51-004-ARL (AFT E\/E SUPP LWR)":1,"21-28-42 (1.1.1.1.1)":1,"21-29":1,"21-30":1,"21-30-00":2,"21-31":17,"21-31 (1.1.1.1)":2,"21-31-00":5,"21-31-00-ZA1-18-001-H-S (1.1)":1,"21-31-02-01B-055 (M00119)":1,"21-31-03-01A-330 (POS1)":1,"21-31-06-01-010":1,"21-31-35 (1.1.1.1.1)":2,"21-31-35-40-030A (102HL)":1,"21-31-58 (1.1.1.1.1)":3,"21-33":3,"21-4 (1.1.1)":1,"21-40":1,"21-42 (1.1.1.1)":2,"21-43-00":2,"21-44":1,"21-5 (1.1.1)":3,"21-50":2,"21-51":35,"21-51-00":15,"21-51-00-ZA1-35-010-H-S (1.1)":2,"21-51-00-ZA1-36-001 (RH-INBOARD)":2,"21-51-00-ZA1-36-010-H-S (1.1)":1,"21-51-00-ZA1-91-001-ARL":1,"21-51-01-01-010B-HTC":1,"21-51-03-02-138 (1.1.1.1.1.1)":1,"21-51-12-01-060 (RH.2)":1,"21-51-21-01-62 (RH)":1,"21-52":26,"21-52 (1.1.1.1)":1,"21-52-00":27,"21-52-00-01-040D":1,"21-52-00-ZA1-35-004":1,"21-52-00-ZA1-36-007 (V2152002)":1,"21-52-00-ZA1-36-009 (RIGHT [B2152008])":1,"21-53":1,"21-53 (1.1.1.1)":2,"21-53-00":37,"21-53-00-ZA1-61-004-HTC (M2153112)":1,"21-53-00-ZA1-61-006-ARL (NO.3)":1,"21-53-00-ZA1-61-007-ARL (NO.2)":3,"21-53-19-20A-941A (1.1.1)":1,"21-53-51 (1.1.1.1.1)":1,"21-54-00":19,"21-58":3,"21-58-61 (1.1.1.1.1)":1,"21-59 (1.1.1.1)":7,"21-59-07 (1.1.1.1.1)":1,"21-59-55 (1.1.1.1.1)":10,"21-6 (1.1.1)":1,"21-60":3,"21-61":12,"21-61-01-01-010G":1,"21-61-07-01-015 (V00002.2)":2,"21-61-12-01B-050 (M01609)":2,"21-61-21-02-265 (V00143,VLV-CONTROL CABIN TRIM MOD":1,"21-72 (1.1.1.1)":1,"21-72-00":2,"21-72-00-ZA2-54-006 (1.1.1)":1,"21-81-00":6,"22":5,"22 (1.1)":3,"22-00":4,"22-10-00-01-020":2,"22-11":12,"22-11 (1.1.1)":1,"22-11-01-01-010E":1,"22-11-11-01-010A":1,"22-11-33-03-10-H-S":2,"22-12":1,"23":26,"23 (1.1)":5,"23-00":31,"23-11":3,"23-11 (1.1.1.1)":4,"23-11-00":6,"23-11-01-01-010 (2)":1,"23-11-33-01-010 (1RE1)":1,"23-11-33-01-010 (1RE2)":1,"23-12":17,"23-12 (1.1.1)":1,"23-12 (1.1.1.1)":2,"23-12-00":11,"23-12-00-ZA2-11-001-H-S (1.1)":2,"23-12-00-ZA2-11-002-H-S (1.1)":1,"23-12-02-01-105 (CTR [M23007])":1,"23-12-41-06-25 (P00871)":1,"23-12-41-09-010 (1.1.1.2)":1,"23-15-00":4,"23-15-10-35B-H (M23106)":1,"23-15-10-35B-H-S (1.1)":1,"23-2 (1.1.1)":2,"23-21":1,"23-22":1,"23-24":1,"23-24-00":1,"23-25 (1.1.1.1)":1,"23-27-00":1,"23-27-51-06B-05-H-S":1,"23-28 (1.1.1.1)":8,"23-31":6,"23-32":10,"23-32-13-22B-10 (RH2)":1,"23-33-56 (1.1.1.1.1)":1,"23-34":5,"23-34 (1.1.1)":2,"23-35":6,"23-35-01-01-010A":1,"23-40":3,"23-41 (1.1.1)":1,"23-42":9,"23-42 (1.1.1)":1,"23-42-01-18-25 (M00074[FWD])":1,"23-43":1,"23-5 (1.1.1)":3,"23-51":16,"23-51 (1.1.1)":4,"23-51 (1.1.1.1)":2,"23-51-00":13,"23-51-00-ZA1-18-001-H-S (1.1)":3,"23-51-00-ZA1-18-002-H-S (1.1)":1,"23-51-00-ZA2-11-002-H-S (1.1)":2,"23-51-00-ZA2-11-004-H-S (1.1)":1,"23-51-02-02-020 (CAPTAIN (P00806))":1,"23-6 (1.1.1)":12,"23-60":2,"23-61":13,"23-61 (1.1.1.1)":1,"23-61-00":20,"23-71":3,"23-71 (1.1.1)":1,"23-75":1,"23-75-00":1,"23-79 (1.1)":1,"23-81":8,"23-81-01-01-010K (Cockpit, Center Console #1)":1,"23-82 (1.1.1)":1,"23-93":2,"24":16,"24 (1.1)":11,"24-00":48,"24-00 (1.1.1)":4,"24-00-00":2,"24-09-00":9,"24-09-00-ZA1-45-005 (P100 RIGHT)":1,"24-10":2,"24-11":5,"24-11-00":2,"24-15-00":12,"24-15-00-ZA1-45-001-H-S":1,"24-15-00-ZA1-46-003-H-S":1,"24-20":2,"24-21":3,"24-21 (1.1.1)":1,"24-21-00":1,"24-21-06-01-010 (2)":1,"24-21-21-01-200":1,"24-21-21-41C-563 (C00801)":1,"24-22 (1.1.1.1)":2,"24-22-00":12,"24-22-00-ZA1-45-002-H-S":1,"24-22-00-ZA1-45-003-H-S":1,"24-25":5,"24-25-00-ZA1-151-001 (1.1)":1,"24-25-09-01-010-H-S (1.1)":1,"24-31":15,"24-31-00":3,"24-31-00-ZA1-18-003 (MAIN)":1,"24-32":9,"24-32-00":1,"24-34":3,"24-34-21-01-05 (M00009)":1,"24-35":4,"24-35-00":1,"24-36-00":9,"24-4 (1.1.1)":5,"24-41":1,"24-41-00":2,"24-5 (1.1.1)":2,"24-7 (1.1.1)":1,"24-71 (1.1.1.1)":16,"24-71-00":8,"24-71-57-01-010 (4383XZ)":1,"24-71-57-01-010 (4386XZ)":1,"24-71-57-01-070 (4321XZ)":1,"24-71-57-01-072 (4312XZ)":1,"24-71-57-04-010B (4559XZ)":1,"24-72 (1.1.1.1)":1,"24-74 (1.1.1.1)":2,"25":197,"25 (1.1)":180,"25-0 (1.1.1)":24,"25-00":93,"25-00 (1.1.1)":4,"25-00-00":4,"25-1 (1.1.1)":8,"25-10":35,"25-10 (1.1.1)":3,"25-11":42,"25-11 (1.1.1)":5,"25-11 (1.1.1.1)":21,"25-11-00":50,"25-11-46 (3MS)":2,"25-12":1,"25-13":13,"25-13 (1.1.1.1)":46,"25-14":1,"25-14-00":7,"25-15":4,"25-15-00":9,"25-16":9,"25-16 (1.1.1.1)":1,"25-2 (1.1.1)":35,"25-20":60,"25-20 (1.1.1)":4,"25-21":32,"25-21 (1.1.1)":8,"25-21 (1.1.1.1)":139,"25-21-00":50,"25-21-44 (1.1.1.1.1)":31,"25-21-45 (1.1.1.1.1)":12,"25-21-46 (1.1.1.1.1)":27,"25-21-47 (1.1.1.1.1)":3,"25-21-48 (1.1.1.1.1)":2,"25-21-49 (1.1.1.1.1)":2,"25-22":215,"25-22 (1.1.1)":47,"25-22 (1.1.1.1)":39,"25-23":7,"25-23 (1.1.1)":2,"25-23 (1.1.1.1)":36,"25-23-00":2,"25-24":65,"25-24 (1.1.1)":15,"25-24 (1.1.1.1)":16,"25-24-00":162,"25-24-41 (1.1.1.1.1)":3,"25-25":167,"25-25 (1.1.1)":2,"25-25 (1.1.1.1)":6,"25-25-00":455,"25-26":13,"25-26 (1.1.1.1)":23,"25-27":14,"25-27 (1.1.1)":2,"25-27 (1.1.1.1)":9,"25-27-00":18,"25-28":3,"25-28 (1.1.1.1)":15,"25-28-00":18,"25-29":13,"25-29 (1.1.1)":1,"25-3 (1.1.1)":101,"25-30":18,"25-30 (1.1.1)":3,"25-31":126,"25-31 (1.1.1)":28,"25-31 (1.1.1.1)":61,"25-31-00":59,"25-31-03-50B-045 (POS1)":1,"25-31-21-21A-231 (AFT 5)":1,"25-31-41-16Q-250. (AFT 3)":1,"25-31-50-20F-040-HTC (AFT GLY LH #1 (A209))":1,"25-31-50-20F-040-HTC (FWD GLY OVEN #3 (F206))":1,"25-31-50-20F-045-HTC (1.7)":1,"25-32":20,"25-32 (1.1.1)":9,"25-32-00":125,"25-32-00-ZA2-00-003 (G1F-1C COMPT F)":1,"25-32-00-ZA2-00-003 (G4A-1C COMPT G)":1,"25-32-00-ZA2-00-003 (G4A-1C COMPT H)":1,"25-32-00-ZA2-00-003-002 (G1F-1C COMPT F.2)":1,"25-32-00-ZA2-00-003-004 (G1F-1C COMPT F.7)":1,"25-32-00-ZA2-00-004 (G1A-1C COMPT D)":1,"25-32-00-ZA2-00-004 (G2A-1C COMPT E)":2,"25-32-00-ZA2-00-004 (G4A-1C COMPT BD)":1,"25-32-00-ZA2-00-006 (G1A-1C COMPT F)":1,"25-32-00-ZA2-00-006 (G4A-1C COMPT K)":1,"25-32-00-ZA2-00-006-008 (G1F-1C COMPT E.2)":1,"25-32-01-14B-420 (4A1C50-AFT)":1,"25-33":5,"25-34":1,"25-35":4,"25-35 (1.1.1.1)":21,"25-35-52-10B (223NL110.5)":1,"25-36 (1.1.1.1)":40,"25-36-43-20 (1.1.1.1.9)":1,"25-36-51 (1021NL181)":1,"25-36-71-30 (745NL120)":1,"25-4 (1.1.1)":43,"25-40":55,"25-40 (1.1.1)":41,"25-40-00 (1.1)":22,"25-41":62,"25-41 (1.1.1)":2,"25-41 (1.1.1.1)":47,"25-41-00":126,"25-41-01-59R-225 (LAV 3F-1L)":1,"25-42":9,"25-42-00 (1.1)":43,"25-44 (1.1.1.1)":1,"25-45 (1.1.1.1)":55,"25-5 (1.1.1)":1,"25-50":57,"25-51":3,"25-51 (1.1.1.1)":9,"25-52":79,"25-53":70,"25-53-01-50A-270 (11)":1,"25-53-01-50A-270 (14)":1,"25-55":2,"25-57":3,"25-57 (1.1)":20,"25-58":5,"25-58 (1.1)":4,"25-6 (1.1.1)":17,"25-60":17,"25-60-99-01-45 (1.1)":1,"25-61":5,"25-61-00":2,"25-62":28,"25-62 (1.1.1.1)":15,"25-62-00":15,"25-62-47-01-010-HTC (7910MX)":1,"25-62-47-01-020-HTC (7911MX)":1,"25-62-47-03-020-HTC (7903MX)":1,"25-63":2,"25-63 (1.1.1)":2,"25-63-00":1,"25-63-00-ZA2-12-001-HTC (1.1)":1,"25-64":55,"25-64 (1.1.1)":14,"25-64 (1.1.1.1)":14,"25-64-00":16,"25-65 (1.1.1.1)":11,"25-66":14,"25-66 (1.1.1)":1,"25-66 (1.1.1.1)":13,"25-66-00":2,"25-66-00-ZA8-43-001-HTC (DR NO.4 LH)":1,"25-67 (1.1.1.1)":2,"25-68 (1.1.1.1)":3,"25-71":1,"25-8 (1.1.1)":1,"25-80-00":1,"26":14,"26 (1.1)":1,"26-00":14,"26-1 (1.1.1)":8,"26-10":1,"26-10-00":1,"26-10-00-ZA4-31-001":1,"26-11":4,"26-11-00":2,"26-12":1,"26-12 (1.1.1.1)":1,"26-12-06-01-005B-HTC (FWD)":1,"26-12-16-01-160 (6WD2)":1,"26-13":1,"26-14":1,"26-15":1,"26-15 (1.1.1)":2,"26-15 (1.1.1.1)":1,"26-15-00":1,"26-16":4,"26-16-00":4,"26-16-00-ZA1-22-004 (1.1)":1,"26-16-00-ZA1-22-005 (1.1)":1,"26-16-01-02-135 (1.13)":1,"26-16-15 (1.1.1.1.1)":1,"26-18":9,"26-19 (1.1)":2,"26-2 (1.1.1)":1,"26-20":1,"26-21-00-ZA1-22-002-HTC (B2621002)":1,"26-22":3,"26-22-01-01-05-HTC":1,"26-23":3,"26-23 (1.1.1.1)":8,"26-23-00":3,"26-23-31 (1.1.1.1.1)":1,"26-24":1,"26-24 (1.1.1.1)":3,"26-24-00-ZAA-41-415-HTC (L2A\/F-1L)":1,"26-24-01-21-001 (1.1)":1,"26-24-61-21-040A (7526WE)":1,"26-25 (1.1.1.1)":1,"26-26":42,"26-26 (1.1.1)":6,"26-26-00":1,"26-26-01-01-010-HTC":1,"26-26-01-16D-05-HTC (1.2)":1,"26-26-01-60B-05-OCCM (FWD)":1,"26-26-02-01F-0200 (RH-FLR-MTD STOWAGE)":1,"26-26-02-02A-01-CARGO-OCCM (COCKPIT)":1,"26-26-02-61F-05-HTC":1,"27":26,"27 (1.1)":35,"27-00":56,"27-00-00":1,"27-02-00":8,"27-02-01-H-S (1.1)":4,"27-03-00":2,"27-09":2,"27-1 (1.1.1)":12,"27-10":4,"27-11":8,"27-11-00":3,"27-14":1,"27-14 (1.1.1.1)":2,"27-14-53 (1.1.1.1.1)":6,"27-14-55 (1.1.1.1.1)":5,"27-2 (1.1.1)":1,"27-21":3,"27-21-00":3,"27-24 (1.1.1.1)":1,"27-24-53 (1.1.1.1.1)":1,"27-3 (1.1.1)":2,"27-30":1,"27-31":4,"27-31-00":2,"27-31-05-01-120-HTC (LCTR)":1,"27-31-05-01-120-HTC (RCTR)":1,"27-33":3,"27-33-01-01-010B (1)":1,"27-34 (1.1.1.1)":1,"27-34-55-01 (1.1.1.1.1)":1,"27-4 (1.1.1)":3,"27-41":3,"27-41-00":9,"27-41-71-01-001 (1.1)":1,"27-48-00-ZA3-11-001 (POS3)":1,"27-5 (1.1.1)":18,"27-50":8,"27-50 (1.1.1)":2,"27-51":14,"27-51 (1.1.1)":2,"27-51-00":9,"27-51-00-ZA6-61-002 (1.1)":1,"27-51-11-01-15 (RH)":1,"27-51-12-01-15 (AFT-RH)":2,"27-51-34 (1.1.1.1.1)":1,"27-52":3,"27-52-16-05-020A (2)":1,"27-54":6,"27-54 (1.1.1.1)":1,"27-54-51 (1.1.1.1.1)":2,"27-54-59 (1.1.1.1.1)":1,"27-58":1,"27-58-00-ZA5-61-001 (LH IBD)":1,"27-58-03-01-030 (RH AFT)":2,"27-59-00":1,"27-6 (1.1.1)":4,"27-61":7,"27-61-00":13,"27-61-00-ZA6-52-010 (1.1)":1,"27-61-00-ZA6-61-012 (RH NO.11)":1,"27-61-11-20-105 (1.1.1.1.1)":1,"27-62":3,"27-62-01-01-010B (1)":1,"27-62-01-01-010B (3)":1,"27-62-01-01-010B (4)":1,"27-63":1,"27-64 (1.1.1.1)":1,"27-64-53 (1.1.1.1.1)":8,"27-64-53-04-310 (4CL1)":1,"27-64-53-05-310 (6CL1)":1,"27-64-55 (1.1.1.1.1)":1,"27-8 (1.1.1)":6,"27-81":9,"27-81 (1.1.1)":5,"27-81-00":15,"27-81-00-ZA5-21-004":1,"27-81-10-02-140 (RH)":1,"27-84 (1.1.1.1)":5,"27-84-52 (1.1.1.1.1)":1,"27-88":3,"27-89-00-ZA5-22-001 (LH)":1,"27-9 (1.1.1)":3,"27-90 (1.1.1.1)":1,"27-92-14-01-070 (5CP)":1,"27-92-16 (1.1.1.1.1)":1,"27-93-34 (1.1.1.1.1)":1,"27-94-34-01-010 (2CE2)":1,"28":13,"28 (1.1)":3,"28-00":19,"28-00-00":2,"28-10":1,"28-10-00":1,"28-11":3,"28-11 (1.1.1.1)":1,"28-18 (1.1.1.1)":3,"28-2 (1.1.1)":1,"28-20":1,"28-21":7,"28-21-00":2,"28-21-00-ZA5-21-003-H-S":1,"28-21-01-10-095 (POS1)":1,"28-21-01-10-095 (POS2)":1,"28-21-03-01-037 (POS1)":1,"28-21-51-01-040B-HTC (102QA1)":1,"28-21-72 (1.1.1.1.1)":1,"28-22":7,"28-22-00":2,"28-22-00-ZA2-12-001-H-S":1,"28-23":1,"28-24":4,"28-24-31-01-020 (1.2)":1,"28-25":4,"28-25 (1.1.1.1)":2,"28-25-25 (1.1.1.1.1)":3,"28-26":2,"28-26-00":2,"28-31":2,"28-31-71 (1.1.1.1.1)":1,"28-40":5,"28-41":9,"28-41-00":5,"28-41-00-ZA1-44-001-H-S":1,"28-41-00-ZA5-52-001-H-S":1,"28-41-00-ZA6-52-001-H (M2841102)":2,"28-42":1,"28-43":1,"28-44":1,"28-5 (1.1.1)":1,"28-51 (1.1.1.1)":3,"29":22,"29 (1.1)":9,"29-00":31,"29-00-00":1,"29-10":2,"29-10 (1.1.1.1)":3,"29-11":30,"29-11 (1.1.1.1)":4,"29-11-00":19,"29-11-00-ZA1-97-003-002 (CTR1)":1,"29-11-01-01-010B (RH)":5,"29-11-11-02-001 (1.1.1.1)":1,"29-11-45 (1.1.1.1.1)":1,"29-11-52-12-001 (1.1)":1,"29-11-56-01-010C\/020C-HTC (2JG2)":5,"29-11-61-01-010":1,"29-11-68 (1.1.1.1.1)":1,"29-12":4,"29-12-21-01-010B":3,"29-13 (1.1.1.1)":3,"29-13-45 (1.1.1.1.1)":3,"29-13-56-01-010C\/020C-HTC (2JY1)":1,"29-13-56-01-010C\/020C-HTC (2JY2)":1,"29-16-55 (1.1.1.1.1)":1,"29-18-00":3,"29-21":2,"29-21-35 (1.1.1.1.1)":1,"29-21-52-01-001 (1.1)":1,"29-23-35-01-110A (2JJ)":1,"29-31":2,"29-31-00":1,"29-32 (1.1.1.1)":1,"29-32-00":1,"29-33":1,"29-33 (1.1.1.1)":1,"29-33-53 (1.1.1.1.1)":1,"29-33-55 (1.1.1.1.1)":1,"30":14,"30 (1.1)":4,"30-00":22,"30-10":4,"30-11":10,"30-11 (1.1.1.1)":1,"30-11-00":8,"30-11-00-ZA5-21-003 (1.1)":1,"30-11-00-ZA5-21-004 (1.1)":1,"30-11-01-01-010":1,"30-11-16-01-060D (2)":1,"30-11-51 (1.1.1.1.1)":1,"30-21":11,"30-21-11-01A-130 (LH)":1,"30-22-00":4,"30-22-01-010-30 (1.1)":6,"30-3 (1.1.1)":1,"30-34":1,"30-40":2,"30-41":4,"30-41 (1.1.1)":1,"30-41-00":1,"30-41-00-ZA2-11-001":1,"30-41-00-ZA2-11-002 (LH)":1,"30-42":11,"30-42-00":1,"30-42-00-ZA2-12-001 (RH)":1,"30-45 (1.1.1.1)":2,"30-61":3,"30-7 (1.1.1)":1,"30-71":1,"30-71-00":3,"30-80":2,"30-80-00-01-010D (1)":2,"30-81 (1.1.1.1)":3,"30-81-15 (1.1.1.1.1)":2,"31":3,"31 (1.1)":8,"31-00":8,"31-00-00":1,"31-1 (1.1.1)":3,"31-11":9,"31-11 (1.1.1.1)":4,"31-11-94-05G-355 (1.1)":1,"31-11-95-05C-30 (P00569)":1,"31-12":2,"31-14":2,"31-19 (1.1.1.1)":1,"31-19-12-03-120C (211VM)":1,"31-19-12-06-070B (221VM)":1,"31-2 (1.1.1)":5,"31-31":10,"31-31 (1.1.1)":1,"31-31-00":3,"31-31-00-ZA2-23-001-H (M3131001 (FWD))":1,"31-31-00-ZA2-64-001-H (M3131002 (AFT))":1,"31-31-03-01-018-H-S":2,"31-31-03-02-011-H-S":1,"31-31-22-04-05-H-S":2,"31-31-22-04-80-H-S":1,"31-33-01-01-H-S (1.1)":1,"31-41":5,"31-41-11-10-H (M31101M003)":1,"31-41-11-10-H (M31201M008)":1,"31-41-11-10-H-S (1.1)":1,"31-41-52-02-005 (N10014[P002-LWR])":2,"31-5 (1.1.1)":3,"31-51":1,"31-51-00":1,"31-53":1,"31-61":6,"31-61 (1.1.1.1)":1,"31-61-00":12,"31-61-00-ZA2-11-006 (LEFT MFK)":1,"31-61-00-ZA2-11-011 (1.1)":1,"31-61-01-01-010H (Zone # 211(Display unit ED))":1,"31-61-01-01-010H (Zone # 211(Display unit MFD #1))":1,"31-61-25-01-010 (1WK22)":1,"31-62":2,"31-62 (1.1.1.1)":1,"31-62-21-09-05-H (M01808)":1,"31-62-21-09-05-H-S":1,"31-65 (1.1.1)":2,"32":167,"32 (1.1)":18,"32-0 (1.1.1)":2,"32-00":162,"32-00-00":3,"32-05":1,"32-08-00":2,"32-09":6,"32-09 (1.1.1)":1,"32-1 (1.1.1)":5,"32-10":10,"32-11":53,"32-11 (1.1.1.1)":10,"32-11-00":10,"32-11-00-01-030C-HTC (LH)":1,"32-11-00-01-030C-HTC (RH)":1,"32-11-00-ZA7-31-054 (POS-05)":1,"32-11-00-ZA7-31-058 (POS-01)":1,"32-11-00-ZA7-31-059 (POS-02)":1,"32-11-00-ZA7-31-061 (POS-06)":1,"32-11-00-ZA7-41-056 (POS-08)":1,"32-11-00-ZA7-41-058 (POS-03)":2,"32-11-00-ZA7-41-059 (POS-04)":2,"32-11-00-ZA7-41-060 (POS-07)":1,"32-11-00-ZA7-41-061 (POS-08)":1,"32-11-01-01-100 (RH)":1,"32-11-60-01-060-HTC (5500GM1) ->32-11-67 (1.1)":1,"32-11-60-01-060-HTC (5500GM1) ->32-11-69 (1.1)":2,"32-11-60-01-060-HTC (5500GM1) ->32-31-94 (1.1)":1,"32-11-60-01-060-HTC (5500GM1) ->32-41-62 (1.1)":13,"32-11-60-01-060-HTC (5500GM1) ->32-42-63 (1.1)":1,"32-11-60-01-060-HTC (5500GM1) ->32-42-63-01-010B (":1,"32-11-60-01-070-HTC (5500GM2) ->32-11-60 (1.1)":1,"32-11-60-01-070-HTC (5500GM2) ->32-11-62 (1.1)":1,"32-11-60-01-070-HTC (5500GM2) ->32-11-69 (1.1)":2,"32-11-60-01-070-HTC (5500GM2) ->32-11-73 (1.1)":1,"32-11-60-01-070-HTC (5500GM2) ->32-41-62 (1.1)":16,"32-11-60-01-070-HTC (5500GM2) ->32-42-63-01-010B (":4,"32-12":8,"32-12-00":10,"32-12-01-01-005 (Aft MLG Door Assy  I\/B(R Nacelle)":1,"32-12-01-01-010 (Aft MLG Door Assy Inbd(L Nacelle)":1,"32-13":3,"32-2 (1.1.1)":4,"32-20":3,"32-21":28,"32-21 (1.1.1)":1,"32-21 (1.1.1.1)":5,"32-21-00":13,"32-21-00-01-001-HTC":1,"32-21-00-01-010K-HTC":4,"32-21-00-01-080B-HTC":1,"32-21-00-ZA7-11-038-H (M3242149)":1,"32-21-01-05-230A":3,"32-22":9,"32-22-00":11,"32-22-00-05-020":1,"32-31":4,"32-31-00":5,"32-31-01-01-010 (1.1)":1,"32-31-11-01-010-HTC (LH)":1,"32-31-11-01-010-HTC (RH)":1,"32-31-46-01-010D-HTC":1,"32-31-66 (1.1.1.1.1)":1,"32-32":9,"32-32-00":2,"32-34":4,"32-35-00":1,"32-4 (1.1.1)":4,"32-40":45,"32-41":113,"32-41 (1.1.1)":2,"32-41-00":9,"32-41-00-ZA1-45-001-H-S":2,"32-41-64 (1.1.1.1.1)":1,"32-42":14,"32-42 (1.1.1.1)":1,"32-42-00":14,"32-42-00-ZA1-13-001-H-S":2,"32-42-00-ZA1-14-001-H-S":1,"32-42-01-01-010B NEW (LH.2)":1,"32-42-01-10B-050 (M00102)":1,"32-42-63 (1.1.1.1.1)":1,"32-43":6,"32-44":8,"32-44-00":5,"32-44-06-01-010":1,"32-45":293,"32-45 (1.1.1)":5,"32-45-00":109,"32-45-01-01B-051-RH-HTC (NO7)":1,"32-45-01-01B-115-LH-OCC (NO1)":1,"32-45-02-01B-095-OCC (NLG RH)":1,"32-45-07-05A-055 (01)":1,"32-45-07-05A-055 (02)":1,"32-45-07-05A-055 (04)":1,"32-45-07-05A-055 (09)":2,"32-45-11-02-18 (NO1)":1,"32-45-11-02-18 (NO2)":1,"32-45-11-02-18RH (NO3)":4,"32-45-21-01-05-HTC (RH)":1,"32-45-21-01-25 (LH)":2,"32-45-21-01-25 (RH)":1,"32-45-21-02-001 (1.1.1.1)":1,"32-45-21-02-005 (1)":1,"32-46":4,"32-46-01-01-010":1,"32-49":13,"32-49 (1.1.1)":1,"32-49-00":2,"32-5 (1.1.1)":1,"32-50-00":2,"32-51":6,"32-51 (1.1.1.1)":2,"32-51-00":7,"32-51-33 (1.1.1.1.1)":1,"32-51-51 (1.1.1.1.1)":1,"32-53":5,"32-60":1,"32-61":4,"32-61-00":2,"33":47,"33 (1.1)":14,"33-00":54,"33-00-00":3,"33-10":3,"33-11":12,"33-11-00":1,"33-12 (1.1.1.1)":2,"33-13":1,"33-13 (1.1.1.1)":2,"33-13-00":2,"33-14":4,"33-14 (1.1.1)":1,"33-17":1,"33-17 (1.1.1)":2,"33-18":1,"33-2 (1.1.1)":4,"33-20":9,"33-20 (1.1.1)":1,"33-21":21,"33-21 (1.1.1)":1,"33-21 (1.1.1.1)":4,"33-21-00":24,"33-22":12,"33-22 (1.1.1)":1,"33-22-00":4,"33-23":2,"33-23 (1.1.1.1)":14,"33-24":4,"33-24-00":2,"33-25":3,"33-25 (1.1.1)":1,"33-25-00":2,"33-26":4,"33-27":5,"33-27 (1.1.1)":2,"33-27-00":2,"33-28-00":1,"33-29":4,"33-29-00":1,"33-3 (1.1.1)":3,"33-30":2,"33-31":4,"33-31-00":12,"33-32":4,"33-34 (1.1.1.1)":1,"33-37":1,"33-37-00":31,"33-4 (1.1.1)":1,"33-40":4,"33-41":18,"33-41 (1.1.1.1)":1,"33-41-00":2,"33-41-13-01-020B (17LA)":2,"33-42":27,"33-42 (1.1.1)":1,"33-42 (1.1.1.1)":2,"33-42-00":2,"33-43":21,"33-43 (1.1.1.1)":2,"33-43-00":12,"33-43-00-ZA6-43-001 (RIGHT)":1,"33-43-04 (L33980 Tail Cone Light)":1,"33-43-12-02-050 (L00042 (RH))":1,"33-43-13-01-010B (24LC)":1,"33-44":16,"33-44 (1.1.1)":1,"33-44 (1.1.1.1)":1,"33-44-00":7,"33-44-02-01A-090 (L00037 [LT-LOWER ANTI-COLLISION ":1,"33-44-04-01-460 (M00570[UPR])":1,"33-44-06-01-010A (Lower Anti-Collision Light)":2,"33-45":13,"33-45-00":8,"33-45-01-01-020":1,"33-45-53-01B-040 (L00434-IB-RH)":1,"33-46 (1.1.1.1)":4,"33-47 (1.1.1.1)":17,"33-47-32-01-040A (3LY1)":1,"33-47-32-01-040A (3LY2)":1,"33-48 (1.1.1.1)":3,"33-49":11,"33-49 (1.1.1)":4,"33-5 (1.1.1)":2,"33-50":6,"33-51":17,"33-51 (1.1.1)":6,"33-51 (1.1.1.1)":10,"33-51-00":13,"33-51-01-01-010-HTC (Zone 235BZ(Cabin Headliner #1":1,"34":19,"34 (1.1)":6,"34-00":22,"34-1 (1.1.1)":1,"34-11":5,"34-11 (1.1.1.1)":3,"34-12":8,"34-12-16-05-020 (Zone 211(Cockpit, Instrument Pane":2,"34-12-34-01-010A (1FP1)":1,"34-13":2,"34-21":13,"34-21 (1.1.1)":5,"34-21-00":7,"34-21-00-01-055B (RIGHT WING TIP)":1,"34-21-00-ZA1-45-001-H-S":2,"34-21-00-ZA1-45-002-H (M3421003 [LEFT])":1,"34-21-00-ZA1-45-002-H-S":2,"34-21-01-01-005-H-S (1.1)":1,"34-21-01-01-05 (RH [M01752])":2,"34-21-01-01B-050 (M00160[CTR])":2,"34-21-02-01-015-H-S (1.1)":2,"34-22":1,"34-22 (1.1.1.1)":1,"34-22-01-01B-020-H-S":3,"34-22-04-01-005 (N00005[P001-CPT])":1,"34-22-25-01-030 (10FC1)":2,"34-23":1,"34-24":3,"34-31":4,"34-31-00":3,"34-31-01-03-010 (LH [M34410])":1,"34-33":3,"34-33-00":2,"34-41":4,"34-41-01-01A-010 (Front Fuse)":1,"34-42 (1.1.1.1)":5,"34-42-00":3,"34-42-00-ZA1-18-005-H (M3442102 [RIGHT])":1,"34-42-00-ZA1-18-005-H-S":1,"34-42-11-01-050 (6SA1)":1,"34-43":11,"34-43-01-02B-205 (M00213 [LH])":1,"34-44":1,"34-44-02-15-080 (2)":1,"34-45":8,"34-45 (1.1.1)":1,"34-46":2,"34-5 (1.1.1)":1,"34-51":5,"34-51 (1.1.1.1)":9,"34-53":4,"34-53 (1.1.1.1)":2,"34-54":3,"34-55":1,"34-55-00":1,"34-57":1,"34-57-01-01-005 (RH [M34208])":1,"34-58":1,"34-58 (1.1.1)":1,"34-60":3,"34-61":12,"34-61 (1.1.1)":1,"34-61-01-02-006-H-S":1,"34-61-01-02-70-H-S":1,"34-61-01-03-05-H-S":1,"34-61-02-02B-05-H-S":3,"34-7 (1.1.1)":2,"34-71 (1.1.1.1)":9,"34-71-33-01-030 (7SE1)":1,"35":34,"35 (1.1)":4,"35-00":13,"35-1 (1.1.1)":4,"35-10":36,"35-11":28,"35-11 (1.1.1.1)":5,"35-11-00":17,"35-11-06-01-010-HTC (OBSERVER)":2,"35-11-51-05B-010-HTC (CAP)":1,"35-11-56 (1.1.1.1.1)":13,"35-12":50,"35-12 (1.1.1)":2,"35-12 (1.1.1.1)":3,"35-12-85-20D-205":1,"35-2 (1.1.1)":4,"35-20":1,"35-20 (1.1)":4,"35-21":13,"35-21 (1.1)":5,"35-21 (1.1.1.1)":4,"35-21-00":8,"35-21-00-20-05 (1.1.1)":1,"35-21-00-20-05B (1.1.1)":1,"35-22":9,"35-22-51-06F-15-HTC (3)":1,"35-23 (1.1.1.1)":1,"35-3 (1.1.1)":14,"35-31":40,"35-31 (1.1.1)":1,"35-31-00-64E-045-HTC (1.4)":1,"35-31-00-ZA2-21-01-HTC (1.1-FLOOR STOWAGE-RH)":1,"35-31-00-ZA2-21-01-HTC (1.17)":1,"35-31-01-05-020-HTC (AFT RH  DOGHOUSE)":1,"35-31-HTC":4,"35-32 (1.1.1.1)":1,"35-32-61-OC (6001HP3)":1,"35-32-61-OC (6008HP1)":1,"35-36-HTC":1,"35-40 (1.1)":2,"36":9,"36 (1.1)":2,"36-00":1,"36-1 (1.1.1)":3,"36-10":1,"36-11":28,"36-11 (1.1.1)":1,"36-11 (1.1.1.1)":2,"36-11-03-02A-15 (LH)":1,"36-11-34 (1.1.1.1.1)":1,"36-11-49 (1.1.1.1.1)":1,"36-11-53 (1.1.1.1.1)":1,"36-11-53-01-100 (15HA2)":1,"36-11-63-01-090 (13HA1)":1,"36-11-63-01-180 (13HA2)":1,"36-12":8,"36-12 (1.1.1)":1,"36-2 (1.1.1)":3,"36-22":1,"38":13,"38 (1.1)":5,"38-00":11,"38-00-00":2,"38-02-05 (1.1.1.1)":1,"38-1 (1.1.1)":15,"38-10":3,"38-10-00":11,"38-11":4,"38-11 (1.1.1.1)":2,"38-11-00":2,"38-11-06-50F-060 (2)":1,"38-12 (1.1.1.1)":11,"38-12-25-55-01-130 (120MB)":1,"38-13 (1.1.1)":2,"38-13 (1.1.1.1)":9,"38-13-00":1,"38-14":2,"38-14 (1.1.1.1)":10,"38-14-00":3,"38-15":1,"38-15-00":1,"38-15-00-ZA1-64-003 (1.1.1)":1,"38-20":4,"38-23":4,"38-3 (1.1.1)":8,"38-30":1,"38-30-00":8,"38-31":5,"38-31 (1.1.1.1)":20,"38-31-00":4,"38-31-00-ZA2-00-001 (L4F-1L)":1,"38-31-01-01-01 (FWD)":1,"38-32":9,"38-32 (1.1.1.1)":4,"38-32-00":6,"38-32-01-07- 30 (ET) (AFT LAV E)":1,"38-33":1,"38-33-00":1,"38-36":2,"38-4 (1.1.1)":1,"38-42":3,"38-42 (1.1.1)":1,"38-42-01-02-310 (1.1.1.1)":1,"38-5 (1.1.1)":8,"38-51 (1.1.1.1)":3,"42 (1.1)":1,"42-00":27,"42-00-00":10,"42-00-00-ZA1-14-010 (LEFT NO.1)":1,"42-00-00-ZA1-14-010 (LEFT NO.2)":1,"42-00-00-ZA1-17-006-H (GPM-L5 [E4220001M5] [LS1876":1,"42-21-00":18,"42-21-00-ZA1-14-007-H":1,"42-21-00-ZA1-17-007-H":1,"42-21-00-ZA2-12-001-H":1,"42-41 (1.1.1.1)":2,"44":15,"44 (1.1)":19,"44-00":9,"44-1 (1.1.1)":11,"44-11 (1.1.1.1)":17,"44-11-00":7,"44-12-00":1,"44-14-00":2,"44-2 (1.1.1)":112,"44-20-00":59,"44-21":10,"44-21 (1.1.1)":9,"44-21 (1.1.1.1)":30,"44-21-00":1,"44-22 (1.1.1.1)":6,"44-22-00":1,"44-24-03-010 (4 C)":1,"44-24-21-02 (SVDU 11-H)":1,"44-24-21-02 (SVDU 16-B)":1,"44-24-21-02 (SVDU 17-C)":1,"44-24-21-02 (SVDU 21-F)":1,"44-24-21-02 (SVDU 23-A)":1,"44-24-21-02 (SVDU 39-B)":1,"44-24-21-04 (SVDU-4-A)":1,"44-24-32 (QSEB-14 ABC)":2,"44-24-32 (QSEB-18 ABC)":1,"44-24-32 (QSEB-22 ABC)":1,"44-24-32 (QSEB-22 DFH)":1,"44-24-32 (QSEB-29 DFH)":1,"44-25-21 (1.1.11)":1,"44-26-00":89,"44-26-00-ZA-10-001 (SDB-12 JKL)":2,"44-26-00-ZA-10-001 (SDB-24 ABC)":1,"44-26-00-ZA-10-001 (SDB-26 DFH)":1,"44-26-00-ZA1-13-001-H-S":1,"44-26-00-ZA1-13-003 (M4421033 [DSU-3])":1,"44-26-00-ZA2-26-001 (MID RH)":1,"44-26-00-ZA2-26-002 (4 H)":1,"44-26-00-ZA2-26-004 (1.18)":1,"44-26-00-ZAA-26-001 (15 F)":1,"44-26-00-ZAA-26-001 (24 K)":1,"44-26-00-ZAA-26-001 (33 H)":1,"44-26-00-ZAA-26-001 (38 F)":1,"44-28 (1.1.1.1)":2,"44-28-61-010 (120MK102)":1,"44-3 (1.1.1)":5,"44-30 (1.1.1)":1,"44-33 (1.1.1.1)":8,"44-34 (1.1.1.1)":2,"44-35 (1.1)":10,"44-35-00 (1.1)":8,"44-5 (1.1.1)":2,"44-52 (1.1.1.1)":4,"44-IFE HARDWARES (1.1)":77,"44-IFE SOFTWARE":3,"45-00":5,"45-10":1,"45-11-00":2,"46":1,"46 (1.1)":5,"46-00":23,"46-00-00":1,"46-1 (1.1.1)":1,"46-10-00":1,"46-11":3,"46-11-00":5,"46-12 (1.1.1.1)":1,"46-12-00":19,"46-12-00-ZA1-17-003-H":1,"46-12-00-ZA1-53-001 (BLW AFT CARGO [CWLU])":1,"46-12-34 (1.1.1.1.1)":1,"46-12-34-01-020 (102TC4)":1,"46-12-35 (1.1.1.1.1)":2,"46-13-00":6,"46-26 (1.1.1.1)":5,"47":15,"47 (1.1)":1,"47-00":13,"47-00-00":1,"47-1 (1.1.1)":1,"47-10 (1.1.1.1)":3,"47-10-62 (1.1.1.1.1)":1,"47-11":12,"47-11-00":16,"47-11-51-01B-120 (POS1)":1,"47-13-00":1,"47-14-00":1,"47-14-00-ZA1-92-002-HTC (1.1)":1,"47-16-00-ZA1-92-001 (1.1)":1,"47-21-00":1,"47-31":3,"47-32":1,"47-32-00":1,"47-41":3,"49":11,"49 (1.1)":2,"49-00":27,"49-10":1,"49-11":1,"49-11-00":2,"49-11-11 (1.1.1.1.1)":1,"49-11-11-01-04A (5100KB) ->49-24 (1.1.1)":1,"49-11-11-01-04A (5100KB) ->49-24-90-05-005A (1.1.1":1,"49-11-11-01-04A (5100KB) ->49-24-90-17-005A (1.1.1":1,"49-11-11-01-04A (5100KB) ->QEC (1.1)":4,"49-12 (1.1.1.1)":1,"49-13 (1.1.1.1)":1,"49-15-00":1,"49-16 (1.1.1.1)":1,"49-21-00":1,"49-22":2,"49-27":1,"49-30":3,"49-30-04-01-010X (POS1)":1,"49-31-00":1,"49-40":3,"49-41":2,"49-41-00":1,"49-42-54-10-190B (21KA)":2,"49-50":10,"49-52":3,"49-60":2,"49-61":6,"49-61-00":1,"49-72":1,"49-81 (1.1.1.1)":1,"49-91":5,"50 (1.1)":67,"50-00":270,"50-00-00":15,"50-1 (1.1.1)":64,"50-10 (1.1.1)":2,"50-11 (1.1.1)":1,"50-11-00":102,"50-12 (1.1.1)":2,"50-13 (1.1.1.1)":200,"50-13-67 (1.1.1.1.1)":11,"50-2 (1.1.1)":22,"50-21-00":91,"50-21-00-ZA1-10-941-155 (M5021519)":1,"50-21-00-ZA1-21-001-A-H (M5021101)":3,"50-21-00-ZA1-22-001-H-S (1.1)":2,"50-21-00-ZA1-22-002-A-H (M5021201)":1,"50-21-00-ZA1-22-003-A-H (M5021208)":1,"50-21-00-ZA1-22-004-A-H (M5021211)":1,"50-21-00-ZA1-22-004-B-H (M5021212)":2,"50-21-00-ZA1-22-006-A-H (M5021204)":1,"50-21-00-ZA1-22-008-A-H (M5021218)":1,"50-21-00-ZA1-51-001-B-H (M5021402)":1,"50-21-00-ZA1-51-002-D-H (M5021410)":1,"50-21-00-ZA1-52-001-H-S (1.1)":1,"50-21-00-ZA1-52-002-B-H (1L)":1,"50-21-00-ZA1-52-003-B-H (M5021504)":1,"50-21-00-ZA1-52-003-C-H (M5021509)":2,"50-21-00-ZA1-52-003-D-H (M5021510)":1,"50-23 (1.1.1.1)":74,"50-23-19 [PDU, SPRING LOADED] (1508MY11)":1,"50-23-19 [PDU, SPRING LOADED] (1508MY12)":1,"50-23-19 [PDU, SPRING LOADED] (1509MY11)":1,"50-23-19 [PDU, SPRING LOADED] (1551MY11)":1,"50-23-63 (1.1.1.1.1)":30,"50-60-00":16,"51":31,"51 (1.1)":24,"51-00":110,"51-00 (1.1)":1,"51-00 (1.1.1)":1,"51-03":2,"51-03-00":2,"51-1 (1.1.1)":1,"51-21 (1.1)":9,"51-21 (1.1.1)":6,"51-21-00":16,"51-25 (1.1.1)":3,"51-4 (1.1.1)":3,"51-41":1,"51-7 (1.1.1)":7,"51-80 (1.1.1)":2,"52":33,"52 (1.1)":15,"52-00":59,"52-05 (1.1)":5,"52-05-00":2,"52-09":9,"52-09-00":1,"52-1 (1.1.1)":15,"52-10":4,"52-11":27,"52-11 (1.1.1)":1,"52-11 (1.1.1.1)":13,"52-11-00":29,"52-11-00-ZA8-32-002-HTC (PED NO.1-RH)":1,"52-11-00-ZA8-43-002-HTC (PED NO.4-LH)":2,"52-12":4,"52-12 (1.1.1.1)":10,"52-13":3,"52-13 (1.1.1)":1,"52-13 (1.1.1.1)":5,"52-20":2,"52-21":6,"52-21 (1.1.1)":3,"52-21-00":2,"52-22":4,"52-22 (1.1.1)":1,"52-23":2,"52-3 (1.1.1)":8,"52-31":16,"52-31 (1.1.1)":3,"52-32":4,"52-32 (1.1)":3,"52-33":8,"52-33 (1.1.1.1)":17,"52-34":7,"52-34-00":12,"52-34-00-ZA1-52-006 (1.1)":1,"52-35":3,"52-35-00":8,"52-36":3,"52-36 (1.1.1.1)":5,"52-36-00":5,"52-36-63 (1.1.1.1.1)":8,"52-37":3,"52-4 (1.1.1)":13,"52-40":3,"52-40-00":11,"52-41":2,"52-41 (1.1.1.1)":15,"52-42":2,"52-43":1,"52-44":2,"52-48":4,"52-49":8,"52-5 (1.1.1)":4,"52-50":3,"52-50 (1.1.1)":1,"52-51":11,"52-51 (1.1.1)":4,"52-51 (1.1.1.1)":13,"52-51-00":7,"52-53-00":5,"52-54":5,"52-70":1,"52-71":2,"52-71 (1.1.1)":1,"52-71 (1.1.1.1)":2,"52-8 (1.1.1)":2,"52-81":4,"52-81 (1.1.1.1)":2,"52-82 (1.1.1.1)":2,"53":31,"53 (1.1)":42,"53-0 (1.1.1)":5,"53-00":53,"53-00-00":5,"53-01":1,"53-01-00":3,"53-05 (1.1)":4,"53-05-00":1,"53-08-00":6,"53-1 (1.1.1)":2,"53-10":2,"53-10-50 (1.1)":2,"53-11":5,"53-11 (1.1.1.1)":1,"53-12":6,"53-12-00":16,"53-12-00-ZA1-11-001-ARL":1,"53-12-01-01-065 (1.1)":1,"53-13":1,"53-14":1,"53-15":1,"53-15 (1.1.1.1)":1,"53-15-73 (1.1.1.1.1)":2,"53-16":3,"53-19 (1.1.1.1)":1,"53-2 (1.1.1)":12,"53-20":4,"53-21 (1.1.1)":2,"53-23":1,"53-3 (1.1.1)":16,"53-30":3,"53-31":3,"53-31 (1.1.1)":2,"53-31 (1.1.1.1)":1,"53-35-75 (1.1.1.1.1)":1,"53-36":1,"53-36-00":1,"53-4 (1.1.1)":15,"53-40":3,"53-41":3,"53-41 (1.1.1.1)":3,"53-43":1,"53-5 (1.1.1)":1,"53-50":1,"53-51 (1.1.1)":1,"53-51 (1.1.1.1)":1,"53-52 (1.1.1)":1,"53-52-00-03A-001 (1.1.1.1)":1,"53-52-00-03A-230":1,"53-58-00":1,"53-63":1,"53-66":1,"53-66-00":1,"53-70-00 (1.1)":3,"53-90-00":6,"53-91":1,"54":14,"54 (1.1)":8,"54-00":19,"54-00-00":3,"54-05":1,"54-1 (1.1.1)":2,"54-10":3,"54-20":3,"54-3 (1.1.1)":2,"54-30":2,"54-31":2,"54-32":1,"54-40 (1.1)":4,"54-5 (1.1.1)":2,"54-50 (1.1.1.1)":1,"54-51":6,"54-52":1,"54-53":5,"54-54":1,"54-61-00":1,"54-62-00":6,"54-63-00":7,"54-65-00":1,"55":6,"55 (1.1)":4,"55-00":6,"55-05-00":1,"55-1 (1.1.1)":6,"55-10":3,"55-10-00":3,"55-11 (1.1.1.1)":2,"55-12 (1.1.1.1)":2,"55-13-00-01-020D":6,"55-13-00-01-030D":1,"55-13-00-01-050D":2,"55-13-00-01-060D":3,"55-16 (1.1.1.1)":4,"55-16-00":1,"55-2 (1.1.1)":1,"55-30":3,"55-30 (1.1.1)":3,"55-31-00":1,"55-33-00-01-010D":2,"55-35":1,"55-40":1,"55-45":1,"56":6,"56 (1.1)":1,"56-00":17,"56-10":22,"56-10 (1.1.1)":2,"56-10-00-01-020D":1,"56-11":11,"56-11-00":16,"56-11-21-01-05 (1.1.1.1)":1,"56-12":4,"56-12 (1.1.1)":2,"56-12-11-01A-011 (1.1.1.1)":1,"56-12-11-01A-011 (NO. 2 LH)":1,"56-2 (1.1.1)":10,"56-20":1,"56-21":5,"56-21-00":13,"56-3 (1.1.1)":3,"56-31 (1.1.1.1)":3,"56-31-00":4,"57":28,"57 (1.1)":51,"57-00":48,"57-00 (1.1.1)":3,"57-00-00":8,"57-05":1,"57-05-00":3,"57-1 (1.1.1)":4,"57-10":1,"57-11":1,"57-13":2,"57-13-00-01-020A (1(LH))":1,"57-13-00-01-030A (RH)":2,"57-15":1,"57-15-00":9,"57-19 (1.1.1.1)":1,"57-2 (1.1.1)":20,"57-20":15,"57-20 (1.1.1)":5,"57-23":15,"57-23-00-01-100A (1(Left Wing Leading Edge))":1,"57-23-00-01-150A (1(Right Wing Leading Edge))":1,"57-23-00-01-190A (1(Right Wing Leading Edge))":2,"57-23-00-01-280A":1,"57-23-00-01-290A":2,"57-24":1,"57-24 (1.1.1.1)":1,"57-25":1,"57-25-00":5,"57-26":2,"57-3 (1.1.1)":5,"57-31 (1.1.1)":2,"57-32":2,"57-4 (1.1.1)":13,"57-40":2,"57-40 (1.1.1)":3,"57-41":11,"57-41 (1.1.1)":3,"57-41 (1.1.1.1)":4,"57-41-00":9,"57-43":2,"57-43 (1.1.1.1)":1,"57-44 (1.1.1.1)":9,"57-44-61 (1.1.1.1.1)":1,"57-45":3,"57-46 (1.1.1.1)":23,"57-5 (1.1.1)":15,"57-50 (1.1.1)":2,"57-51":7,"57-51 (1.1.1.1)":7,"57-51-00":7,"57-52":5,"57-52 (1.1)":1,"57-53":8,"57-53 (1.1.1.1)":2,"57-54":1,"57-54 (1.1.1.1)":1,"57-56 (1.1.1.1)":3,"57-57 (1.1.1.1)":8,"57-6 (1.1.1)":1,"57-61 (1.1.1.1)":2,"57-63":6,"57-71 (1.1.1.1)":2,"61":9,"61-10":15,"61-20":3,"70 (1.1)":1,"70-00":2,"71":21,"71 (1.1)":8,"71-00":21,"71-00 (1.1.1.1)":2,"71-00-00":5,"71-00-01-02E-530 (RH IB)":1,"71-1 (1.1.1)":6,"71-10":21,"71-10-00":7,"71-10-00-01-030A":1,"71-10-00-01-300J (1.1)":2,"71-10-00-05-300J (1.1)":1,"71-11":17,"71-11 (1.1.1)":2,"71-11-00":13,"71-11-00-ZA4-12-001":2,"71-11-00-ZA4-13-002":1,"71-11-00-ZA4-22-001":2,"71-11-01 (1.1)":1,"71-12":2,"71-12-00-HTC":2,"71-12-01-01-50-RHOB (RIGHT ENGINE OUTBOARD)":1,"71-13 (1.1.1.1)":8,"71-13-63 (1.1.1.1.1)":1,"71-13-64 (1.1.1.1.1)":1,"71-20":2,"71-21":11,"71-21-00-01-010A-HTC (LH ENG FWD 1)":2,"71-21-00-01-010A-HTC (LH ENG FWD 2)":2,"71-21-00-01-020A-HTC (RH ENG FWD 2)":1,"71-21-00-01-030-HTC (RH ENG TOP)":1,"71-21-00-01-040-HTC (LH ENG AFT 1)":1,"71-22":1,"71-22 (1.1.1.1)":1,"71-40-62 (1.1.1.1.1)":1,"71-50":1,"71-51":1,"71-60-61 (1.1.1.1.1)":10,"71-61":2,"71-71":1,"71-71 (1.1.1.1)":1,"71-71-63 (1.1.1.1.1)":3,"72":18,"72 (1.1)":8,"72-00":75,"72-00 (1.1.1)":12,"72-00-00":8,"72-10":1,"72-2 (1.1.1)":1,"72-20-00":3,"72-21":14,"72-21 (1.1.1)":5,"72-21-00":5,"72-22 (1.1.1)":2,"72-22-00":19,"72-23 (1.1.1)":5,"72-24":6,"72-25-00":3,"72-30-00":1,"72-31-62 (1.1.1.1.1)":1,"72-33 (1.1.1.1)":1,"72-35 (1.1.1.1)":3,"72-35-63 (1.1.1.1.1)":2,"72-35-64 (1.1.1.1.1)":1,"72-35-65 (1.1.1.1.1)":1,"72-40":1,"72-50-00":2,"72-53":2,"72-54":3,"72-64":1,"73":14,"73 (1.1)":6,"73-00":16,"73-20":2,"73-20-00":1,"73-21":5,"73-21-00":3,"73-33 (1.1.1.1)":1,"73-34-00":1,"74":3,"74-00":1,"74-11":1,"74-21 (1.1.1)":1,"74-21-00":1,"75":8,"75-00":11,"75-11-00":1,"75-20-00":1,"75-23-00":1,"75-24":1,"75-24 (1.1.1.1)":5,"75-24-00":3,"75-31":1,"76":2,"76-11":1,"76-11 (1.1.1)":1,"76-11-00":3,"77":4,"77 (1.1)":2,"77-00":10,"77-12-00":2,"77-31":3,"77-31 (1.1.1)":1,"77-31-00":1,"77-31-04-01F-010-H-S (1.1)":1,"78":13,"78 (1.1)":9,"78-00":18,"78-10":5,"78-10-01-01-005":1,"78-11":3,"78-11-00":1,"78-3 (1.1.1)":3,"78-30":3,"78-30 (1.1)":1,"78-30-00":5,"78-31":18,"78-31-00":11,"78-31-01 (1.1)":4,"78-32 (1.1.1.1)":9,"78-32-61 (1.1.1.1.1)":1,"78-34":5,"78-34 (1.1.1)":1,"78-34-00":1,"78-34-07-03-001 (1.1)":2,"78-36":1,"78-36 (1.1.1.1)":1,"79":6,"79 (1.1)":2,"79-00":24,"79-00-00":2,"79-10-00":1,"79-11":1,"79-21":6,"79-21 (1.1.1.1)":1,"79-22":1,"79-31":2,"79-33":1,"79-34 (1.1.1.1)":1,"79-35":1,"80":2,"80 (1.1)":1,"80-11":1,"80-11 -00":1,"91-13 (1.1.1.1)":1,"91-14 (1.1.1.1)":1,"91-15 (1.1.1.1)":2,"92 (1.1)":1,"APS1000 APU":22,"APS1000 APU->49-11 (1.1)":4,"APS1000 APU->49-11-00-01-020A-HTC (APU DC STARTER)":1,"APS1000 APU->49-20":5,"APS1000 APU->49-20-01-01-150":1,"APS1000 APU->49-24":2,"APS1000 APU->49-40 (1.1)":2,"APS1000 APU->QEC (1.1)":3,"APU 131-9B (737MAX APU) ->49-26-93-20-020":1,"APU 131-9B (737MAX APU) ->QEC":1,"APU 131-9B (737NG APU)":3,"APU 131-9B (737NG APU) ->49-26-93-03-020":1,"APU 131-9B (737NG APU) ->49-26-93-20-020":1,"APU 131-9B (737NG APU) ->QEC":7,"APU APS5000":5,"APU APS5000->24-21-00-ZA3-15-001 (LH)":3,"APU APS5000->24-21-00-ZA3-15-002 (RH)":2,"APU APS5000->49-00":1,"APU APS5000->QEC":14,"APU APS5000->UNTRKD":1,"APU331-200->QEC":1,"APU331-5 (APU)":4,"APU331-5 (APU) ->49-11":2,"APU331-5 (APU) ->49-26-55-11-050":1,"APU331-5 (APU) ->QEC (1.1)":2,"CMM 21-58-51-630 (202HH1)":1,"CMM25-36-04-03 (AFT GLY RH #1 (A310).12)":1,"CMM27-52-40-090 (81CV)":1,"CMM27-54-20-030 (24CV)":1,"ENGINE (LH)":1,"ENGINE (LH) ->72-00":5,"ENGINE (LH) ->72-00-00-09-230 (01)":1,"ENGINE (LH) ->72-00-00-09-230 (09)":2,"ENGINE (LH) ->72-00-00-09-230 (12)":2,"ENGINE (LH) ->72-00-06-50-001 (1.1)":2,"ENGINE (LH) ->72-21":8,"ENGINE (LH) ->72-23":1,"ENGINE (LH) ->73-21":1,"ENGINE (LH) ->74-11-10-01-010 (2)":1,"ENGINE (LH) ->75-32":1,"ENGINE (LH) ->78-11":1,"ENGINE (LH) ->79":1,"ENGINE (LH) ->QEC (1.1)":12,"ENGINE (RH)":1,"ENGINE (RH) ->24-25-01-02B-200 (1.1.1.1)":1,"ENGINE (RH) ->72":3,"ENGINE (RH) ->72-00":4,"ENGINE (RH) ->72-00-00-09-230 (19)":3,"ENGINE (RH) ->72-00-06-50-001 (1.1)":2,"ENGINE (RH) ->72-21":5,"ENGINE (RH) ->72-24":2,"ENGINE (RH) ->73-11":1,"ENGINE (RH) ->74-11-10-01-010 (2)":1,"ENGINE (RH) ->77-11":1,"ENGINE (RH) ->QEC (1.1)":10,"LH ENG - 787-8 (LH)":17,"LH ENG - 787-8 (LH) ->71-21-00":1,"LH ENG - 787-8 (LH) ->72 (1.1)":2,"LH ENG - 787-8 (LH) ->72-00":8,"LH ENG - 787-8 (LH) ->72-00 (1.1.1)":5,"LH ENG - 787-8 (LH) ->72-00-00":6,"LH ENG - 787-8 (LH) ->72-22-00-ZA9-03-001 (1.2)":1,"LH ENG - 787-8 (LH) ->72-22-00-ZA9-03-001 (1.6)":1,"LH ENG - 787-8 (LH) ->72-31 (1.1.1)":1,"LH ENG - 787-8 (LH) ->72-31-00-01-780 (1.1)":1,"LH ENG - 787-8 (LH) ->72-40-00":2,"LH ENG - 787-8 (LH) ->72-50-00":4,"LH ENG - 787-8 (LH) ->72-53-00-01-130":1,"LH ENG - 787-8 (LH) ->72-53-00-01-250":1,"LH ENG - 787-8 (LH) ->73 (1.1)":1,"LH ENG - 787-8 (LH) ->73-00":2,"LH ENG - 787-8 (LH) ->73-11-01 (1.1)":1,"LH ENG - 787-8 (LH) ->73-21-00-ZA9-03-001 (1.1)":1,"LH ENG - 787-8 (LH) ->73-21-11-01-250 (1.1.1)":1,"LH ENG - 787-8 (LH) ->73-22-00":1,"LH ENG - 787-8 (LH) ->74 (1.1)":1,"LH ENG - 787-8 (LH) ->75-00":2,"LH ENG - 787-8 (LH) ->75-33-15-01-250 (1.1.1)":1,"LH ENG - 787-8 (LH) ->77-32-10-01-060 (1.1.1)":1,"LH ENG - 787-8 (LH) ->78-31-00":1,"LH ENG - 787-8 (LH) ->79-32-00":2,"LH ENG - 787-8 (LH) ->QEC":43,"LH ENG - 787-8 (LH) ->QEC (1.1)":18,"LH ENG - 787-8 (LH) ->UNTRACKED":1,"LH ENG - A350-900\/1000 (LH)":2,"LH ENG - A350-900\/1000 (LH) ->11 (1.1)":4,"LH ENG - A350-900\/1000 (LH) ->24 (1.1)":1,"LH ENG - A350-900\/1000 (LH) ->36 (1.1)":4,"LH ENG - A350-900\/1000 (LH) ->72 (1.1)":2,"LH ENG - A350-900\/1000 (LH) ->72-00 (1.1.1)":1,"LH ENG - A350-900\/1000 (LH) ->72-35 (1.1.1)":2,"LH ENG - A350-900\/1000 (LH) ->72-41 (1.1.1)":3,"LH ENG - A350-900\/1000 (LH) ->73 (1.1)":4,"LH ENG - A350-900\/1000 (LH) ->75-33-15-02-250 (1.1":1,"LH ENG - A350-900\/1000 (LH) ->80 (1.1)":2,"LH ENG - A350-900\/1000 (LH) ->80-11 (1.1.1)":2,"LH ENG - A350-900\/1000 (LH) ->QEC (1.1)":4,"LH ENG - A350-900\/1000 (LH) ->UNTRKD (1.1)":1,"LH ENG-737-MAX (LH) ->72-00 (1.1.1)":2,"LH ENG-737-MAX (LH) ->75-21 (1.1.1)":1,"LH ENG-737-MAX (LH) ->QEC (1.1)":5,"LH ENGINE CFM56-7B (LH)":1,"LH ENGINE CFM56-7B (LH) ->26":1,"LH ENGINE CFM56-7B (LH) ->29-11-11-02A-25":1,"LH ENGINE CFM56-7B (LH) ->36-11-06-02-015":1,"LH ENGINE CFM56-7B (LH) ->71":2,"LH ENGINE CFM56-7B (LH) ->72":1,"LH ENGINE CFM56-7B (LH) ->72-00":6,"LH ENGINE CFM56-7B (LH) ->72-21":2,"LH ENGINE CFM56-7B (LH) ->72-21-00-01-150 (1.18)":1,"LH ENGINE CFM56-7B (LH) ->72-21-00-01-150 (1.6)":1,"LH ENGINE CFM56-7B (LH) ->72-63":1,"LH ENGINE CFM56-7B (LH) ->73-21-10-01-010":1,"LH ENGINE CFM56-7B (LH) ->75":1,"LH ENGINE CFM56-7B (LH) ->77":1,"LH ENGINE CFM56-7B (LH) ->79-21-20-01-010":1,"LH ENGINE CFM56-7B (LH) ->80":1,"LH ENGINE CFM56-7B (LH) ->QEC":27,"NOSE LANDING GEAR ASSY (5500GN) ->32-21-01 (1.1)":2,"NOSE LANDING GEAR ASSY (5500GN) ->32-41-61 (1.1)":3,"PROP150A (LT)":13,"PROP150A (LT) ->61":3,"PROP150A (LT) ->61-00 (1.1)":4,"PROP150A (LT) ->61-10":23,"PROP150A (LT) ->61-10-06-01-001-HTC":1,"PROP150A (LT) ->61-10-11-01-001 (1)":1,"PROP150A (LT) ->61-20":3,"PROP150A (LT) ->61-20-36-01-005":1,"PROP150A (RT)":14,"PROP150A (RT) ->61":1,"PROP150A (RT) ->61-00 (1.1)":1,"PROP150A (RT) ->61-10":16,"PROP150A (RT) ->61-10-01-01-001-HTC (1)":1,"PROP150A (RT) ->61-10-01-01-001-HTC (2)":1,"PROP150A (RT) ->61-10-01-01-001-HTC (3)":1,"PROP150A (RT) ->61-10-01-01-001-HTC (5)":2,"PROP150A (RT) ->61-10-01-01-001-HTC (6)":1,"PROP150A (RT) ->61-10-06-01-001-HTC":6,"PROP150A (RT) ->61-20":2,"PROP150A (RT) ->61-20-36-01-005":2,"PROP150A (RT) ->UNTRKD (1.1)":2,"PW150A ENGINE-HTC (LH)":17,"PW150A ENGINE-HTC (LH) ->24":2,"PW150A ENGINE-HTC (LH) ->24-21-01-01-020B-HTC (AC ":1,"PW150A ENGINE-HTC (LH) ->24-31-01-01-070A-HTC (1.2":1,"PW150A ENGINE-HTC (LH) ->24-31-01-01-070A-HTC (DC ":2,"PW150A ENGINE-HTC (LH) ->72-00":3,"PW150A ENGINE-HTC (LH) ->72-31-00-03-150B":1,"PW150A ENGINE-HTC (LH) ->72-34-00-03-220":1,"PW150A ENGINE-HTC (LH) ->72-41":1,"PW150A ENGINE-HTC (LH) ->73":2,"PW150A ENGINE-HTC (LH) ->73-11-00-11-010":1,"PW150A ENGINE-HTC (LH) ->73-21":3,"PW150A ENGINE-HTC (LH) ->73-21-00-03-010":1,"PW150A ENGINE-HTC (LH) ->73-21-00-05-010":1,"PW150A ENGINE-HTC (LH) ->75-31":1,"PW150A ENGINE-HTC (LH) ->77-11":2,"PW150A ENGINE-HTC (LH) ->QEC (1.1)":1,"PW150A ENGINE-HTC (RH)":14,"PW150A ENGINE-HTC (RH) ->72":1,"PW150A ENGINE-HTC (RH) ->72-00":2,"PW150A ENGINE-HTC (RH) ->72-11-00-01-001":1,"PW150A ENGINE-HTC (RH) ->72-21-00-07-001":1,"PW150A ENGINE-HTC (RH) ->72-32-00-17-230":1,"PW150A ENGINE-HTC (RH) ->72-34":2,"PW150A ENGINE-HTC (RH) ->72-34-00-03-220":2,"PW150A ENGINE-HTC (RH) ->72-34-00-09-001":2,"PW150A ENGINE-HTC (RH) ->72-41":1,"PW150A ENGINE-HTC (RH) ->72-41-00-06-001":1,"PW150A ENGINE-HTC (RH) ->72-51-00-02-070":1,"PW150A ENGINE-HTC (RH) ->72-53-00-03-040":3,"PW150A ENGINE-HTC (RH) ->72-53-00-04-001":2,"PW150A ENGINE-HTC (RH) ->72-53-00-04-040":1,"PW150A ENGINE-HTC (RH) ->73":1,"PW150A ENGINE-HTC (RH) ->73-11":2,"PW150A ENGINE-HTC (RH) ->73-12":1,"PW150A ENGINE-HTC (RH) ->73-21-00-03-010":2,"PW150A ENGINE-HTC (RH) ->73-31-11-01-010 (1.1.1.1)":1,"PW150A ENGINE-HTC (RH) ->75-31":2,"PW150A ENGINE-HTC (RH) ->75-31-00-04-010":1,"PW150A ENGINE-HTC (RH) ->79":1,"PW150A ENGINE-HTC (RH) ->79-22":1,"PW150A ENGINE-HTC (RH) ->QEC (1.1)":3,"QEC (1.1)":1,"RH ENG - 787-8 (RH)":17,"RH ENG - 787-8 (RH) ->71-21-00-ZA4-15-001 (1)":2,"RH ENG - 787-8 (RH) ->72-00":5,"RH ENG - 787-8 (RH) ->72-00 (1.1.1)":1,"RH ENG - 787-8 (RH) ->72-00-00":8,"RH ENG - 787-8 (RH) ->72-00-00-01-004 (1.1)":2,"RH ENG - 787-8 (RH) ->72-00-02-33-012A (1.1.1)":1,"RH ENG - 787-8 (RH) ->72-22-00":1,"RH ENG - 787-8 (RH) ->72-25-00-10-230 (1.1)":1,"RH ENG - 787-8 (RH) ->72-31-00-01-580":1,"RH ENG - 787-8 (RH) ->72-31-00-01-740":1,"RH ENG - 787-8 (RH) ->72-31-00-01-780 (1.1)":1,"RH ENG - 787-8 (RH) ->72-40-00":1,"RH ENG - 787-8 (RH) ->72-41-00-01-080":1,"RH ENG - 787-8 (RH) ->72-50-00":1,"RH ENG - 787-8 (RH) ->72-52 (1.1.1)":1,"RH ENG - 787-8 (RH) ->72-53-00-01-130":1,"RH ENG - 787-8 (RH) ->72-53-00-01-280":1,"RH ENG - 787-8 (RH) ->73-00":3,"RH ENG - 787-8 (RH) ->73-11-00-ZA9-03-001 (1.1)":2,"RH ENG - 787-8 (RH) ->73-11-01 (1.1)":2,"RH ENG - 787-8 (RH) ->73-21-00":1,"RH ENG - 787-8 (RH) ->73-21-00-ZA9-03-001 (1.1)":1,"RH ENG - 787-8 (RH) ->73-21-30-01-010A (1.1)":1,"RH ENG - 787-8 (RH) ->73-21-55-01-010 (1.1)":1,"RH ENG - 787-8 (RH) ->74 (1.1)":1,"RH ENG - 787-8 (RH) ->75 (1.1)":1,"RH ENG - 787-8 (RH) ->75-00":1,"RH ENG - 787-8 (RH) ->77-00":1,"RH ENG - 787-8 (RH) ->77-32-10-01-060 (1.1.1)":1,"RH ENG - 787-8 (RH) ->79-00":1,"RH ENG - 787-8 (RH) ->79-33-10-01-060 (1.1)":1,"RH ENG - 787-8 (RH) ->QEC":40,"RH ENG - 787-8 (RH) ->QEC (1.1)":10,"RH ENG - 787-8 (RH) ->UNTRKD (1.1)":1,"RH ENG - A350-900\/1000 (RH) ->36-11-54-01-010 (1.1":1,"RH ENG - A350-900\/1000 (RH) ->72-35 (1.1.1)":2,"RH ENG - A350-900\/1000 (RH) ->72-41 (1.1.1)":1,"RH ENG - A350-900\/1000 (RH) ->72-51 (1.1.1)":1,"RH ENG - A350-900\/1000 (RH) ->73-21-11-01-250A (40":1,"RH ENG - A350-900\/1000 (RH) ->74-21-12 (1.1.1.1)":1,"RH ENG - A350-900\/1000 (RH) ->75 (1.1)":1,"RH ENG - A350-900\/1000 (RH) ->77 (1.1)":1,"RH ENG - A350-900\/1000 (RH) ->78-11-61-01-070A (1.":1,"RH ENG - A350-900\/1000 (RH) ->QEC (1.1)":8,"RH ENG - A350-900\/1000 (RH) ->UNTRKD (1.1)":1,"RH ENG-737-MAX (RH) ->78 (1.1)":1,"RH ENG-737-MAX (RH) ->QEC (1.1)":2,"RH ENG-767-300 (RH)":4,"RH ENG-767-300 (RH) ->72-00":1,"RH ENG-767-300 (RH) ->72-41":1,"RH ENG-767-300 (RH) ->QEC":4,"RH ENGINE CFM56-7B (RH)":8,"RH ENGINE CFM56-7B (RH) ->26":2,"RH ENGINE CFM56-7B (RH) ->26-11-01-02-200 (1)":1,"RH ENGINE CFM56-7B (RH) ->30-21-11-01A-130 (1.1)":1,"RH ENGINE CFM56-7B (RH) ->36-11-04-01A-20":1,"RH ENGINE CFM56-7B (RH) ->72":1,"RH ENGINE CFM56-7B (RH) ->72-00":1,"RH ENGINE CFM56-7B (RH) ->72-21":2,"RH ENGINE CFM56-7B (RH) ->72-21-00-01-150 (1.11)":2,"RH ENGINE CFM56-7B (RH) ->72-21-00-01-150 (1.19)":1,"RH ENGINE CFM56-7B (RH) ->72-21-00-01-150 (1.23)":1,"RH ENGINE CFM56-7B (RH) ->72-21-00-01-150 (1.4)":1,"RH ENGINE CFM56-7B (RH) ->72-31-00-01-510-2":1,"RH ENGINE CFM56-7B (RH) ->72-31-00-01-530":1,"RH ENGINE CFM56-7B (RH) ->72-31-00-01-550":1,"RH ENGINE CFM56-7B (RH) ->72-52":1,"RH ENGINE CFM56-7B (RH) ->72-54-00-10-390A":1,"RH ENGINE CFM56-7B (RH) ->73-11-10-01-010":1,"RH ENGINE CFM56-7B (RH) ->73-21-10-01-010":1,"RH ENGINE CFM56-7B (RH) ->75-22":1,"RH ENGINE CFM56-7B (RH) ->77":1,"RH ENGINE CFM56-7B (RH) ->79":1,"RH ENGINE CFM56-7B (RH) ->79-21":1,"RH ENGINE CFM56-7B (RH) ->80":1,"RH ENGINE CFM56-7B (RH) ->QEC":40,"RH ENGINE CFM56-7B (RH) ->UNTRKD":1,"UNTK (1.1)":2,"UNTRACKED":1},"by_fleet_ata_seq":{"737":{"Unknown":30,"05":9,"05-00":38,"05-51":2,"06-10":10,"09-11":1,"10":1,"11":8,"11-00":6,"11-20":1,"11-21":1,"11-23":1,"11-24":1,"11-24 (1.1.1)":1,"11-25":2,"11-30":2,"11-31":1,"12":2,"12-12":1,"20":4,"20 (1.1)":1,"20-40":1,"20-60":3,"21":21,"21-00":3,"21-23":1,"21-27":2,"21-30":1,"21-31":3,"21-33":3,"21-50":2,"21-51":20,"21-51-21-01-62 (RH)":1,"21-60":3,"21-61":7,"21-61-21-02-265 (V00143,VLV-CONTROL CABIN TRIM MOD":1,"22":5,"22-11":10,"22-11-33-03-10-H-S":2,"23":15,"23 (1.1)":1,"23-00":6,"23-12":4,"23-12-41-06-25 (P00871)":1,"23-22":1,"23-27-51-06B-05-H-S":1,"23-31":3,"23-32":1,"23-32-13-22B-10 (RH2)":1,"23-34":4,"23-34 (1.1.1)":1,"23-40":3,"23-42":8,"23-42-01-18-25 (M00074[FWD])":1,"23-51":4,"23-60":2,"23-61":4,"23-71":1,"23-75":1,"23-79 (1.1)":1,"24":3,"24 (1.1)":1,"24-00":2,"24-10":2,"24-21":2,"24-21-21-41C-563 (C00801)":1,"24-31":1,"24-34":3,"24-34-21-01-05 (M00009)":1,"24-41":1,"25":115,"25 (1.1)":3,"25-00":8,"25-10":26,"25-11":29,"25-13":10,"25-20":34,"25-20 (1.1.1)":1,"25-21":19,"25-21 (1.1.1)":1,"25-22":205,"25-23":4,"25-24":27,"25-25":27,"25-27":7,"25-27 (1.1.1)":1,"25-29":3,"25-29 (1.1.1)":1,"25-30":17,"25-31":71,"25-31-21-21A-231 (AFT 5)":1,"25-31-41-16Q-250. (AFT 3)":1,"25-40":53,"25-40 (1.1.1)":1,"25-41":16,"25-50":24,"25-52":17,"25-60":5,"25-61":3,"25-64":52,"25-66":11,"26":3,"26-10":1,"26-11":3,"26-14":1,"26-16":1,"26-18":2,"26-19 (1.1)":2,"26-22":2,"26-23":1,"26-24-01-21-001 (1.1)":1,"26-26":19,"26-26-01-16D-05-HTC (1.2)":1,"26-26-01-60B-05-OCCM (FWD)":1,"26-26-02-61F-05-HTC":1,"27":14,"27 (1.1)":1,"27-00":1,"27-09":1,"27-11":3,"27-21":1,"27-30":1,"27-31":2,"27-41":1,"27-41-71-01-001 (1.1)":1,"27-50":5,"27-51":9,"27-51-11-01-15 (RH)":1,"27-51-12-01-15 (AFT-RH)":2,"27-61":5,"27-62":3,"27-81":3,"27-88":3,"28":7,"28 (1.1)":1,"28-10":1,"28-11":2,"28-21":4,"28-22":3,"28-25":2,"28-40":3,"28-41":6,"28-42":1,"28-43":1,"29":4,"29-10":2,"29-11":9,"29-11-52-12-001 (1.1)":1,"29-21":1,"29-21-52-01-001 (1.1)":1,"29-33":1,"30":3,"30-00":1,"30-21":3,"30-21-11-01A-130 (LH)":1,"30-40":2,"30-42":6,"31-11":5,"31-11-94-05G-355 (1.1)":1,"31-11-95-05C-30 (P00569)":1,"31-31":3,"31-31-22-04-05-H-S":2,"31-31-22-04-80-H-S":1,"31-62":2,"31-62-21-09-05-H (M01808)":1,"31-62-21-09-05-H-S":1,"32":101,"32-09":6,"32-10":6,"32-11":8,"32-13":3,"32-20":3,"32-21":13,"32-22":1,"32-32":1,"32-40":37,"32-41":15,"32-42":3,"32-43":6,"32-44":3,"32-45":223,"32-45-11-02-18 (NO1)":1,"32-45-11-02-18 (NO2)":1,"32-45-11-02-18RH (NO3)":4,"32-45-21-01-05-HTC (RH)":1,"32-45-21-01-25 (LH)":2,"32-45-21-01-25 (RH)":1,"32-60":1,"33":25,"33-10":3,"33-11":6,"33-14":4,"33-17":1,"33-18":1,"33-20":7,"33-20 (1.1.1)":1,"33-21":16,"33-22":11,"33-23":1,"33-25":1,"33-27":3,"33-29":4,"33-32":2,"33-40":3,"33-41":1,"33-42":18,"33-43":17,"33-43-12-02-050 (L00042 (RH))":1,"33-44":8,"33-45":6,"33-49":11,"33-50":6,"33-51":6,"34":14,"34-11":1,"34-21":1,"34-21-01-01-05 (RH [M01752])":2,"34-24":1,"34-31":1,"34-43":3,"34-45":6,"34-51":2,"34-53":2,"34-55":1,"34-57":1,"34-58 (1.1.1)":1,"34-60":3,"34-61":4,"34-61-01-02-70-H-S":1,"34-61-01-03-05-H-S":1,"34-61-02-02B-05-H-S":3,"35":22,"35-00":1,"35-10":19,"35-12":50,"35-12-85-20D-205":1,"35-21 (1.1)":2,"35-22":9,"35-31":22,"36":2,"36-00":1,"36-11":1,"36-11-03-02A-15 (LH)":1,"36-12":1,"38":8,"38-10":1,"38-11":4,"38-31":3,"38-32":5,"38-32-01-07- 30 (ET) (AFT LAV E)":1,"38-33":1,"38-42":3,"44":6,"44-21":10,"47":7,"47-00":1,"47-31":2,"47-41":3,"49":2,"49-00":1,"49-10":1,"49-40":3,"49-41":2,"49-52":3,"49-61":2,"49-91":5,"51":3,"51-00":12,"51-21 (1.1)":8,"51-21 (1.1.1)":1,"51-41":1,"52":7,"52-09":2,"52-11":11,"52-13":1,"52-20":2,"52-21":1,"52-22":3,"52-31":7,"52-40":1,"52-41":1,"52-50":3,"52-50 (1.1.1)":1,"52-51":6,"53":10,"53-00":10,"53-11":2,"53-12":1,"53-13":1,"53-14":1,"53-31":3,"53-41":3,"53-52-00-03A-230":1,"54":6,"54-51":1,"54-53":1,"55":3,"55-10":3,"55-30":1,"55-30 (1.1.1)":1,"56":2,"56-00":1,"56-10":15,"56-10 (1.1.1)":2,"56-11":4,"56-12":4,"56-12 (1.1.1)":2,"56-12-11-01A-011 (NO. 2 LH)":1,"56-21":2,"57":7,"57 (1.1)":1,"57-00":4,"57-20":14,"57-20 (1.1.1)":1,"57-40":1,"57-52":5,"57-53":1,"71":4,"71-10":2,"71-11":9,"71-20":1,"71-51":1,"72":12,"72-00":9,"72-21":3,"72-53":2,"72-54":1,"73":9,"73-20":2,"73-21":1,"74":1,"74-21 (1.1.1)":1,"75":7,"75-00":2,"76":1,"76-11":1,"77":4,"77-31":1,"78":5,"78-11":3,"78-30":3,"78-31":5,"78-34":2,"78-34-07-03-001 (1.1)":2,"78-36":1,"79":1,"79-00":2,"APU 131-9B (737NG APU)":3,"APU 131-9B (737NG APU) ->49-26-93-03-020":1,"APU 131-9B (737NG APU) ->49-26-93-20-020":1,"APU 131-9B (737NG APU) ->QEC":7,"LH ENGINE CFM56-7B (LH)":1,"LH ENGINE CFM56-7B (LH) ->26":1,"LH ENGINE CFM56-7B (LH) ->29-11-11-02A-25":1,"LH ENGINE CFM56-7B (LH) ->36-11-06-02-015":1,"LH ENGINE CFM56-7B (LH) ->71":2,"LH ENGINE CFM56-7B (LH) ->72":1,"LH ENGINE CFM56-7B (LH) ->72-00":6,"LH ENGINE CFM56-7B (LH) ->72-21":2,"LH ENGINE CFM56-7B (LH) ->72-21-00-01-150 (1.18)":1,"LH ENGINE CFM56-7B (LH) ->72-21-00-01-150 (1.6)":1,"LH ENGINE CFM56-7B (LH) ->72-63":1,"LH ENGINE CFM56-7B (LH) ->73-21-10-01-010":1,"LH ENGINE CFM56-7B (LH) ->75":1,"LH ENGINE CFM56-7B (LH) ->77":1,"LH ENGINE CFM56-7B (LH) ->79-21-20-01-010":1,"LH ENGINE CFM56-7B (LH) ->80":1,"LH ENGINE CFM56-7B (LH) ->QEC":27,"RH ENGINE CFM56-7B (RH)":8,"RH ENGINE CFM56-7B (RH) ->26":2,"RH ENGINE CFM56-7B (RH) ->26-11-01-02-200 (1)":1,"RH ENGINE CFM56-7B (RH) ->30-21-11-01A-130 (1.1)":1,"RH ENGINE CFM56-7B (RH) ->36-11-04-01A-20":1,"RH ENGINE CFM56-7B (RH) ->72":1,"RH ENGINE CFM56-7B (RH) ->72-00":1,"RH ENGINE CFM56-7B (RH) ->72-21":2,"RH ENGINE CFM56-7B (RH) ->72-21-00-01-150 (1.11)":2,"RH ENGINE CFM56-7B (RH) ->72-21-00-01-150 (1.19)":1,"RH ENGINE CFM56-7B (RH) ->72-21-00-01-150 (1.23)":1,"RH ENGINE CFM56-7B (RH) ->72-21-00-01-150 (1.4)":1,"RH ENGINE CFM56-7B (RH) ->72-31-00-01-510-2":1,"RH ENGINE CFM56-7B (RH) ->72-31-00-01-530":1,"RH ENGINE CFM56-7B (RH) ->72-31-00-01-550":1,"RH ENGINE CFM56-7B (RH) ->72-52":1,"RH ENGINE CFM56-7B (RH) ->72-54-00-10-390A":1,"RH ENGINE CFM56-7B (RH) ->73-11-10-01-010":1,"RH ENGINE CFM56-7B (RH) ->73-21-10-01-010":1,"RH ENGINE CFM56-7B (RH) ->75-22":1,"RH ENGINE CFM56-7B (RH) ->77":1,"RH ENGINE CFM56-7B (RH) ->79":1,"RH ENGINE CFM56-7B (RH) ->79-21":1,"RH ENGINE CFM56-7B (RH) ->80":1,"RH ENGINE CFM56-7B (RH) ->QEC":40,"RH ENGINE CFM56-7B (RH) ->UNTRKD":1},"737MAX":{"Unknown":5,"05 (1.1)":2,"05-00 (1.1.1)":22,"05-51 (1.1.1)":1,"06 (1.1)":1,"06-10 (1.1.1)":14,"11 (1.1)":9,"11-20 (1.1.1)":1,"11-25 (1.1.1)":1,"11-26 (1.1.1)":1,"11-30 (1.1.1)":1,"21 (1.1)":2,"21-23 (1.1.1)":1,"21-24 (1.1.1)":1,"21-25 (1.1.1)":1,"21-51-03-02-138 (1.1.1.1.1.1)":1,"22 (1.1)":2,"22-11 (1.1.1)":1,"23 (1.1)":3,"23-12 (1.1.1)":1,"23-12-41-09-010 (1.1.1.2)":1,"23-34 (1.1.1)":1,"23-41 (1.1.1)":1,"23-42 (1.1.1)":1,"23-51 (1.1.1)":4,"23-51-02-02-020 (CAPTAIN (P00806))":1,"23-71 (1.1.1)":1,"23-82 (1.1.1)":1,"24-00 (1.1.1)":1,"24-21 (1.1.1)":1,"25 (1.1)":21,"25-00 (1.1.1)":4,"25-10 (1.1.1)":3,"25-11 (1.1.1)":5,"25-20 (1.1.1)":3,"25-21 (1.1.1)":7,"25-22 (1.1.1)":47,"25-23 (1.1.1)":2,"25-24 (1.1.1)":15,"25-25 (1.1.1)":2,"25-27 (1.1.1)":1,"25-30 (1.1.1)":3,"25-31 (1.1.1)":28,"25-32 (1.1.1)":9,"25-40 (1.1.1)":40,"25-41 (1.1.1)":2,"25-63 (1.1.1)":2,"25-64 (1.1.1)":14,"25-66 (1.1.1)":1,"26-15 (1.1.1)":2,"26-26 (1.1.1)":6,"26-26-01-01-010-HTC":1,"27 (1.1)":2,"27-50 (1.1.1)":2,"27-51 (1.1.1)":2,"27-61-11-20-105 (1.1.1.1.1)":1,"27-81 (1.1.1)":5,"29 (1.1)":1,"29-11-11-02-001 (1.1.1.1)":1,"30 (1.1)":1,"30-41 (1.1.1)":1,"31 (1.1)":1,"31-31 (1.1.1)":1,"31-65 (1.1.1)":2,"32 (1.1)":3,"32-09 (1.1.1)":1,"32-21 (1.1.1)":1,"32-41 (1.1.1)":2,"32-45 (1.1.1)":5,"32-45-21-02-001 (1.1.1.1)":1,"32-45-21-02-005 (1)":1,"32-49 (1.1.1)":1,"33 (1.1)":3,"33-14 (1.1.1)":1,"33-17 (1.1.1)":2,"33-21 (1.1.1)":1,"33-22 (1.1.1)":1,"33-25 (1.1.1)":1,"33-27 (1.1.1)":2,"33-42 (1.1.1)":1,"33-44 (1.1.1)":1,"33-44-02-01A-090 (L00037 [LT-LOWER ANTI-COLLISION ":1,"33-49 (1.1.1)":4,"33-51 (1.1.1)":6,"34 (1.1)":2,"34-21 (1.1.1)":5,"34-45 (1.1.1)":1,"34-61 (1.1.1)":1,"35 (1.1)":2,"35-12 (1.1.1)":2,"35-31 (1.1.1)":1,"36-11 (1.1.1)":1,"36-12 (1.1.1)":1,"38 (1.1)":1,"38-02-05 (1.1.1.1)":1,"38-13 (1.1.1)":2,"38-42 (1.1.1)":1,"38-42-01-02-310 (1.1.1.1)":1,"44 (1.1)":5,"44-21 (1.1.1)":9,"44-30 (1.1.1)":1,"46 (1.1)":1,"50 (1.1)":1,"50-10 (1.1.1)":2,"50-11 (1.1.1)":1,"50-12 (1.1.1)":2,"51 (1.1)":2,"51-00 (1.1.1)":1,"51-21 (1.1.1)":2,"52 (1.1)":1,"52-11 (1.1.1)":1,"52-13 (1.1.1)":1,"52-21 (1.1.1)":3,"52-22 (1.1.1)":1,"52-31 (1.1.1)":3,"52-51 (1.1.1)":4,"52-71 (1.1.1)":1,"53-21 (1.1.1)":2,"53-31 (1.1.1)":2,"53-51 (1.1.1)":1,"53-52 (1.1.1)":1,"53-52-00-03A-001 (1.1.1.1)":1,"54 (1.1)":3,"55 (1.1)":1,"55-30 (1.1.1)":2,"56-11-21-01-05 (1.1.1.1)":1,"56-12-11-01A-011 (1.1.1.1)":1,"57 (1.1)":7,"57-00 (1.1.1)":3,"57-20 (1.1.1)":4,"57-31 (1.1.1)":2,"57-40 (1.1.1)":3,"57-41 (1.1.1)":3,"57-50 (1.1.1)":2,"71 (1.1)":2,"71-11 (1.1.1)":2,"72 (1.1)":3,"72-00 (1.1.1)":4,"72-21 (1.1.1)":5,"72-22 (1.1.1)":2,"72-23 (1.1.1)":5,"73 (1.1)":2,"76-11 (1.1.1)":1,"77-31 (1.1.1)":1,"78 (1.1)":1,"78-34 (1.1.1)":1,"80 (1.1)":1,"APU 131-9B (737MAX APU) ->49-26-93-20-020":1,"APU 131-9B (737MAX APU) ->QEC":1,"LH ENG-737-MAX (LH) ->72-00 (1.1.1)":2,"LH ENG-737-MAX (LH) ->75-21 (1.1.1)":1,"LH ENG-737-MAX (LH) ->QEC (1.1)":5,"RH ENG-737-MAX (RH) ->78 (1.1)":1,"RH ENG-737-MAX (RH) ->QEC (1.1)":2},"767":{"Unknown":4,"05":4,"05-00":9,"05-41":7,"06":3,"06-10":12,"06-42":3,"11":4,"11-00":8,"11-20":1,"11-22":1,"11-24":1,"11-25":1,"12-15":2,"20":3,"20-10":1,"21":6,"21-00":1,"21-31-02-01B-055 (M00119)":1,"21-40":1,"21-44":1,"21-51":1,"21-51-12-01-060 (RH.2)":1,"21-53":1,"21-58":3,"21-61":1,"21-61-07-01-015 (V00002.2)":2,"21-61-12-01B-050 (M01609)":2,"22-12":1,"23":3,"23-00":1,"23-12":3,"23-24":1,"23-32":9,"23-34":1,"23-42":1,"23-43":1,"23-51":3,"23-61":2,"24":2,"24-11":1,"24-20":1,"24-21":1,"24-31":6,"25":9,"25-10":4,"25-11":3,"25-13":1,"25-20":7,"25-21":2,"25-25":26,"25-27":2,"25-28":1,"25-29":1,"25-31":15,"25-33":1,"25-40":2,"25-41":4,"25-50":19,"25-52":2,"25-53":21,"25-53-01-50A-270 (11)":1,"25-53-01-50A-270 (14)":1,"25-55":2,"25-57":3,"25-58":5,"25-60":4,"25-60-99-01-45 (1.1)":1,"25-61":1,"25-62":1,"25-63":1,"25-64":2,"25-66":2,"26":1,"26-11":1,"26-15":1,"26-16":1,"26-20":1,"26-22":1,"26-23":1,"26-26":5,"26-26-02-02A-01-CARGO-OCCM (COCKPIT)":1,"27":5,"27-09":1,"27-10":2,"27-11":1,"27-21":1,"27-31":1,"27-31-05-01-120-HTC (LCTR)":1,"27-31-05-01-120-HTC (RCTR)":1,"27-41":1,"27-51":1,"28":1,"28-26":2,"28-41":1,"29":6,"29-11":5,"29-21":1,"30-34":1,"31-11":2,"31-12":1,"31-31":4,"31-31-03-01-018-H-S":2,"31-31-03-02-011-H-S":1,"31-41":3,"31-41-52-02-005 (N10014[P002-LWR])":2,"32":5,"32-00":1,"32-05":1,"32-10":4,"32-11":2,"32-12":1,"32-21":2,"32-32":6,"32-41":1,"32-42":2,"32-42-01-10B-050 (M00102)":1,"32-45":15,"32-45-01-01B-051-RH-HTC (NO7)":1,"32-45-01-01B-115-LH-OCC (NO1)":1,"32-45-02-01B-095-OCC (NLG RH)":1,"32-46":1,"32-61":1,"33":7,"33-00":1,"33-11":1,"33-20":2,"33-21":1,"33-24":1,"33-25":1,"33-26":1,"33-27":2,"33-30":1,"33-31":1,"33-37":1,"33-41":4,"33-44":5,"33-44-04-01-460 (M00570[UPR])":1,"33-45":2,"33-45-53-01B-040 (L00434-IB-RH)":1,"33-51":1,"34":1,"34-12":2,"34-13":2,"34-21-01-01B-050 (M00160[CTR])":2,"34-22":1,"34-22-01-01B-020-H-S":3,"34-22-04-01-005 (N00005[P001-CPT])":1,"34-31":1,"34-43":2,"34-43-01-02B-205 (M00213 [LH])":1,"34-45":1,"34-46":1,"34-53":1,"34-58":1,"34-61-01-02-006-H-S":1,"35":1,"35-11":4,"35-11-51-05B-010-HTC (CAP)":1,"35-21":1,"35-31":3,"36":1,"36-10":1,"36-11":2,"38":1,"38-11-06-50F-060 (2)":1,"38-15":1,"38-30":1,"38-31":1,"38-32":1,"47":1,"47-31":1,"49":1,"49-00":2,"49-27":1,"49-61":4,"49-72":1,"51":1,"51-00":4,"52":4,"52-00":2,"52-09":1,"52-11":1,"52-22":1,"52-32 (1.1)":1,"52-33":7,"52-34":1,"52-36":1,"53":1,"53-12":3,"53-16":2,"53-30":1,"54":4,"54-00":1,"54-05":1,"54-51":2,"54-53":1,"55":2,"56-11":2,"57":5,"57-05":1,"57-40":1,"57-41":7,"57-51":6,"71":1,"71-00":1,"71-00-01-02E-530 (RH IB)":1,"71-11":2,"72":1,"72-00":3,"72-54":2,"73":1,"74":2,"74-00":1,"78":3,"78-30 (1.1)":1,"78-31":4,"79":1,"79-33":1,"80":2,"APU331-200->QEC":1,"RH ENG-767-300 (RH)":4,"RH ENG-767-300 (RH) ->72-00":1,"RH ENG-767-300 (RH) ->72-41":1,"RH ENG-767-300 (RH) ->QEC":4},"777":{"Unknown":32,"05 (1.1)":7,"05-00 (1.1.1)":22,"05-41 (1.1.1)":21,"05-42 (1.1.1)":7,"05-51 (1.1.1)":1,"05-55 (1.1.1)":1,"06-10 (1.1.1)":1,"06-21 (1.1.1)":1,"06-43 (1.1.1)":1,"10 (1.1)":1,"11":21,"11-21":1,"11-22":8,"11-23":5,"11-24":1,"11-30":2,"11-37":4,"11-38":2,"12-21 (1.1.1)":2,"20 (1.1)":1,"20-60 (1.1.1)":1,"21":4,"21-21":1,"21-26":2,"21-26-01-15-090 (POS1)":1,"21-29":1,"21-31":5,"21-51":5,"21-52":19,"23-12":1,"23-15-10-35B-H (M23106)":1,"23-15-10-35B-H-S (1.1)":1,"23-51":1,"23-61":5,"23-71":1,"24":2,"24-11":1,"24-25":4,"24-25-09-01-010-H-S (1.1)":1,"24-35":2,"25":27,"25-00":8,"25-10":3,"25-11":3,"25-15":1,"25-20":13,"25-21":11,"25-24":24,"25-25":94,"25-27":2,"25-28":1,"25-29":5,"25-31":27,"25-31-50-20F-040-HTC (AFT GLY LH #1 (A209))":1,"25-31-50-20F-040-HTC (FWD GLY OVEN #3 (F206))":1,"25-31-50-20F-045-HTC (1.7)":1,"25-32":9,"25-33":1,"25-41":30,"25-41-01-59R-225 (LAV 3F-1L)":1,"25-42":9,"25-50":8,"25-52":33,"25-53":39,"25-57 (1.1)":1,"25-60":7,"25-62":17,"25-64":1,"25-66":1,"26":8,"26-16":2,"26-18":7,"26-23":1,"26-26":9,"26-26-02-01F-0200 (RH-FLR-MTD STOWAGE)":1,"27":2,"27-02-01-H-S (1.1)":2,"27-10":1,"27-11":1,"27-51":1,"27-58":1,"27-61":1,"27-81":2,"28":1,"28-21":2,"28-21-03-01-037 (POS1)":1,"28-31":1,"28-41":2,"28-44":1,"29":2,"29-11":4,"29-31":1,"30-21":3,"30-42":2,"30-71":1,"31-41-11-10-H (M31101M003)":1,"31-41-11-10-H (M31201M008)":1,"31-41-11-10-H-S (1.1)":1,"32":1,"32-11":2,"32-21":3,"32-22":1,"32-32":1,"32-42":1,"32-45":19,"32-45-07-05A-055 (01)":1,"32-45-07-05A-055 (04)":1,"32-45-07-05A-055 (09)":1,"32-49":7,"32-51":1,"32-53":1,"33":4,"33-21":4,"33-22":1,"33-23":1,"33-24":2,"33-26":2,"33-40":1,"33-42":1,"33-45":2,"33-51":6,"34-11":1,"34-21":2,"34-23":1,"34-24":1,"34-31":1,"34-33":1,"34-43":1,"34-45":1,"34-46":1,"34-53":1,"35":1,"35-10":1,"35-11":11,"35-20":1,"35-21":12,"35-31":15,"35-31-00-64E-045-HTC (1.4)":1,"36":3,"36-11":5,"36-12":6,"36-22":1,"38":2,"38-10":2,"38-14":2,"38-32":3,"38-36":2,"44":9,"44-24-21-02 (SVDU 11-H)":1,"44-24-21-02 (SVDU 16-B)":1,"44-24-21-02 (SVDU 17-C)":1,"44-24-21-02 (SVDU 21-F)":1,"44-24-21-02 (SVDU 23-A)":1,"44-24-21-02 (SVDU 39-B)":1,"44-24-21-04 (SVDU-4-A)":1,"44-24-32 (QSEB-14 ABC)":2,"44-24-32 (QSEB-18 ABC)":1,"44-24-32 (QSEB-22 ABC)":1,"44-24-32 (QSEB-22 DFH)":1,"44-24-32 (QSEB-29 DFH)":1,"44-25-21 (1.1.11)":1,"44-35 (1.1)":10,"44-IFE HARDWARES (1.1)":77,"44-IFE SOFTWARE":3,"46":1,"46-11":1,"47":2,"47-11":8,"51":20,"51-03":2,"52":4,"52-05 (1.1)":3,"52-09":2,"52-11":5,"52-12":1,"52-34":3,"52-35":1,"52-36":1,"52-37":1,"52-48":1,"52-49":2,"52-51":1,"52-54":5,"52-71":2,"52-81":4,"53":10,"53-00":4,"53-01":1,"53-05 (1.1)":4,"53-30":1,"53-36":1,"53-43":1,"53-66":1,"53-91":1,"54":1,"54-10":3,"54-20":2,"54-30":1,"54-40 (1.1)":2,"54-51":3,"54-52":1,"54-54":1,"55-30":2,"55-35":1,"55-45":1,"56-11":4,"56-21":3,"57":2,"57-00":5,"57-15":1,"57-26":1,"57-41":3,"57-45":3,"57-53":2,"57-63":5,"71":6,"71-11":5,"71-12":2,"72":1,"72-00":13,"72-21":8,"72-24":4,"75-24":1,"76":1,"77-31-04-01F-010-H-S (1.1)":1,"78":1,"78-31":3,"78-34":1,"79":1,"79-21":1,"79-31":1,"APU331-5 (APU)":2,"CMM25-36-04-03 (AFT GLY RH #1 (A310).12)":1,"ENGINE (LH)":1,"ENGINE (LH) ->72-00":3,"ENGINE (LH) ->72-00-00-09-230 (09)":2,"ENGINE (LH) ->72-00-00-09-230 (12)":2,"ENGINE (LH) ->72-00-06-50-001 (1.1)":1,"ENGINE (LH) ->72-21":3,"ENGINE (LH) ->72-23":1,"ENGINE (LH) ->75-32":1,"ENGINE (LH) ->79":1,"ENGINE (LH) ->QEC (1.1)":5,"ENGINE (RH)":1,"ENGINE (RH) ->24-25-01-02B-200 (1.1.1.1)":1,"ENGINE (RH) ->72":1,"ENGINE (RH) ->72-00":2,"ENGINE (RH) ->72-00-00-09-230 (19)":2,"ENGINE (RH) ->72-21":3,"ENGINE (RH) ->73-11":1,"ENGINE (RH) ->74-11-10-01-010 (2)":1,"ENGINE (RH) ->77-11":1,"ENGINE (RH) ->QEC (1.1)":3},"777F":{"Unknown":4,"05 (1.1)":3,"05-00 (1.1.1)":9,"05-41 (1.1.1)":8,"05-42 (1.1.1)":3,"05-55 (1.1.1)":1,"06-10 (1.1.1)":2,"11":5,"11-21":1,"11-22":4,"11-23":1,"11-25":2,"11-32":2,"11-37":1,"20-60 (1.1.1)":1,"21":1,"21-23":2,"21-31":2,"21-31-03-01A-330 (POS1)":1,"21-51":1,"21-52":4,"23":3,"23-12":4,"23-12-02-01-105 (CTR [M23007])":1,"23-21":1,"23-61":2,"23-93":2,"24":1,"24-11":3,"24-25":1,"24-31":2,"24-32":1,"24-35":2,"25":11,"25-10":1,"25-11":5,"25-13":1,"25-24":2,"25-25":10,"25-27":2,"25-29":4,"25-30":1,"25-31":10,"25-31-03-50B-045 (POS1)":1,"25-32":6,"25-50":6,"25-52":18,"25-53":10,"25-57 (1.1)":19,"25-58 (1.1)":4,"25-60":1,"25-71":1,"26-16-01-02-135 (1.13)":1,"26-26":9,"27":4,"27-02-01-H-S (1.1)":2,"27-11":3,"27-21":1,"27-41":1,"27-51":3,"27-58-03-01-030 (RH AFT)":2,"27-61":1,"27-81":4,"27-81-10-02-140 (RH)":1,"28":3,"28-11":1,"28-21":1,"28-21-01-10-095 (POS1)":1,"28-21-01-10-095 (POS2)":1,"28-22":4,"28-25":2,"28-31":1,"29":4,"29-11":3,"29-31":1,"30":1,"30-21":1,"31-11":1,"31-31":3,"31-33-01-01-H-S (1.1)":1,"31-61":2,"32":7,"32-11":2,"32-22":3,"32-32":1,"32-41":3,"32-42":4,"32-44":1,"32-45":36,"32-45-07-05A-055 (02)":1,"32-45-07-05A-055 (09)":1,"32-49":6,"32-51":2,"32-53":4,"33":5,"33-11":5,"33-13":1,"33-26":1,"33-30":1,"33-31":2,"33-42":4,"33-43":4,"33-43-04 (L33980 Tail Cone Light)":1,"33-44":3,"33-45":2,"34":1,"34-21":1,"34-21-01-01-005-H-S (1.1)":1,"34-21-02-01-015-H-S (1.1)":2,"34-24":1,"34-31":1,"34-31-01-03-010 (LH [M34410])":1,"34-33":2,"34-57-01-01-005 (RH [M34208])":1,"34-61":1,"35":3,"35-10":3,"35-11":8,"35-22-51-06F-15-HTC (3)":1,"36-11":12,"36-12":1,"45-10":1,"46-11":2,"47":5,"47-11":4,"47-11-51-01B-120 (POS1)":1,"47-32":1,"49":2,"49-11":1,"51":7,"51-00 (1.1)":1,"51-21 (1.1)":1,"52":6,"52-05 (1.1)":2,"52-09":4,"52-11":2,"52-32 (1.1)":2,"52-33":1,"52-34":3,"52-35":2,"52-36":1,"52-37":2,"52-48":3,"52-49":6,"53":4,"53-00":1,"53-10":1,"53-11":2,"53-12-01-01-065 (1.1)":1,"53-15":1,"53-16":1,"53-63":1,"54":2,"54-20":1,"54-30":1,"54-40 (1.1)":2,"54-53":3,"55":1,"55-40":1,"56":1,"56-11":1,"57":8,"57-10":1,"57-26":1,"57-41":1,"57-43":2,"57-53":4,"57-63":1,"71":2,"71-11":1,"72":2,"72-00":4,"72-21":3,"72-24":2,"72-64":1,"73":3,"73-21":4,"77-31":2,"78":2,"78-31":6,"78-34":2,"79":2,"79-11":1,"79-21":1,"79-31":1,"80-11":1,"APU331-5 (APU)":2,"APU331-5 (APU) ->49-11":2,"APU331-5 (APU) ->49-26-55-11-050":1,"APU331-5 (APU) ->QEC (1.1)":2,"ENGINE (LH) ->72-00":2,"ENGINE (LH) ->72-00-00-09-230 (01)":1,"ENGINE (LH) ->72-00-06-50-001 (1.1)":1,"ENGINE (LH) ->72-21":5,"ENGINE (LH) ->73-21":1,"ENGINE (LH) ->74-11-10-01-010 (2)":1,"ENGINE (LH) ->78-11":1,"ENGINE (LH) ->QEC (1.1)":7,"ENGINE (RH) ->72":2,"ENGINE (RH) ->72-00":2,"ENGINE (RH) ->72-00-00-09-230 (19)":1,"ENGINE (RH) ->72-00-06-50-001 (1.1)":2,"ENGINE (RH) ->72-21":2,"ENGINE (RH) ->72-24":2,"ENGINE (RH) ->QEC (1.1)":7},"787":{"Unknown":153,"05-00":176,"05-00-00":24,"05-41-00":89,"05-51-00":2,"06-00":44,"06-10-00":9,"06-24-00":1,"06-41-00":2,"06-43-00":3,"06-44-00":4,"08-00":1,"10-00":4,"11-00":100,"11-21-00":44,"11-23-00":16,"11-24-00":1,"11-25-00":11,"11-31-00":3,"11-32-00":7,"11-37-00":9,"12-00":29,"12-13-00":4,"12-15-00":2,"12-21-00":8,"20-00":28,"20-10-00":2,"20-30-00":1,"20-41-00":1,"20-60-00":1,"21-00":103,"21-00-00":3,"21-20-00":2,"21-21-00":1,"21-22-00":1,"21-23-00":2,"21-24-00":2,"21-24-01-ZA1-005 (1.1)":1,"21-25-00":4,"21-26-00":14,"21-27-00":10,"21-27-00-ZA1-51-004-ARL (AFT E\/E SUPP LWR)":1,"21-30-00":2,"21-31-00":5,"21-31-00-ZA1-18-001-H-S (1.1)":1,"21-43-00":2,"21-51-00":15,"21-51-00-ZA1-35-010-H-S (1.1)":2,"21-51-00-ZA1-36-001 (RH-INBOARD)":2,"21-51-00-ZA1-36-010-H-S (1.1)":1,"21-51-00-ZA1-91-001-ARL":1,"21-52-00":27,"21-52-00-ZA1-35-004":1,"21-52-00-ZA1-36-007 (V2152002)":1,"21-52-00-ZA1-36-009 (RIGHT [B2152008])":1,"21-53-00":37,"21-53-00-ZA1-61-004-HTC (M2153112)":1,"21-53-00-ZA1-61-006-ARL (NO.3)":1,"21-53-00-ZA1-61-007-ARL (NO.2)":3,"21-53-19-20A-941A (1.1.1)":1,"21-54-00":19,"21-72-00":2,"21-72-00-ZA2-54-006 (1.1.1)":1,"21-81-00":6,"22-00":4,"23-00":24,"23-11-00":6,"23-12-00":11,"23-12-00-ZA2-11-001-H-S (1.1)":2,"23-12-00-ZA2-11-002-H-S (1.1)":1,"23-15-00":4,"23-24-00":1,"23-27-00":1,"23-51-00":13,"23-51-00-ZA1-18-001-H-S (1.1)":3,"23-51-00-ZA1-18-002-H-S (1.1)":1,"23-51-00-ZA2-11-002-H-S (1.1)":2,"23-51-00-ZA2-11-004-H-S (1.1)":1,"23-61-00":20,"23-75-00":1,"24-00":44,"24-00-00":2,"24-09-00":9,"24-09-00-ZA1-45-005 (P100 RIGHT)":1,"24-11-00":2,"24-15-00":12,"24-15-00-ZA1-45-001-H-S":1,"24-15-00-ZA1-46-003-H-S":1,"24-21-00":1,"24-22-00":12,"24-22-00-ZA1-45-002-H-S":1,"24-22-00-ZA1-45-003-H-S":1,"24-25-00-ZA1-151-001 (1.1)":1,"24-31-00":3,"24-31-00-ZA1-18-003 (MAIN)":1,"24-32-00":1,"24-35-00":1,"24-36-00":9,"24-41-00":2,"24-71-00":8,"25-00":75,"25-00-00":4,"25-11-00":50,"25-14-00":7,"25-15-00":9,"25-21-00":50,"25-23-00":2,"25-24-00":162,"25-25-00":455,"25-27-00":18,"25-28-00":18,"25-31-00":59,"25-32-00":125,"25-32-00-ZA2-00-003 (G1F-1C COMPT F)":1,"25-32-00-ZA2-00-003 (G4A-1C COMPT G)":1,"25-32-00-ZA2-00-003 (G4A-1C COMPT H)":1,"25-32-00-ZA2-00-003-002 (G1F-1C COMPT F.2)":1,"25-32-00-ZA2-00-003-004 (G1F-1C COMPT F.7)":1,"25-32-00-ZA2-00-004 (G1A-1C COMPT D)":1,"25-32-00-ZA2-00-004 (G2A-1C COMPT E)":2,"25-32-00-ZA2-00-004 (G4A-1C COMPT BD)":1,"25-32-00-ZA2-00-006 (G1A-1C COMPT F)":1,"25-32-00-ZA2-00-006 (G4A-1C COMPT K)":1,"25-32-00-ZA2-00-006-008 (G1F-1C COMPT E.2)":1,"25-32-01-14B-420 (4A1C50-AFT)":1,"25-40-00 (1.1)":22,"25-41-00":126,"25-42-00 (1.1)":43,"25-61-00":2,"25-62-00":15,"25-63-00":1,"25-63-00-ZA2-12-001-HTC (1.1)":1,"25-64-00":16,"25-66-00":2,"25-66-00-ZA8-43-001-HTC (DR NO.4 LH)":1,"25-80-00":1,"26-00":13,"26-10-00":1,"26-10-00-ZA4-31-001":1,"26-11-00":2,"26-15-00":1,"26-16-00":4,"26-16-00-ZA1-22-004 (1.1)":1,"26-16-00-ZA1-22-005 (1.1)":1,"26-21-00-ZA1-22-002-HTC (B2621002)":1,"26-23-00":3,"26-24-00-ZAA-41-415-HTC (L2A\/F-1L)":1,"26-26-00":1,"27-00":54,"27-00-00":1,"27-02-00":8,"27-03-00":2,"27-11-00":3,"27-21-00":3,"27-31-00":2,"27-41-00":9,"27-48-00-ZA3-11-001 (POS3)":1,"27-51-00":9,"27-51-00-ZA6-61-002 (1.1)":1,"27-58-00-ZA5-61-001 (LH IBD)":1,"27-59-00":1,"27-61-00":13,"27-61-00-ZA6-52-010 (1.1)":1,"27-61-00-ZA6-61-012 (RH NO.11)":1,"27-81-00":15,"27-81-00-ZA5-21-004":1,"27-89-00-ZA5-22-001 (LH)":1,"28-00":18,"28-00-00":2,"28-10-00":1,"28-21-00":2,"28-21-00-ZA5-21-003-H-S":1,"28-22-00":2,"28-22-00-ZA2-12-001-H-S":1,"28-26-00":2,"28-41-00":5,"28-41-00-ZA1-44-001-H-S":1,"28-41-00-ZA5-52-001-H-S":1,"28-41-00-ZA6-52-001-H (M2841102)":2,"29-00":27,"29-00-00":1,"29-11-00":19,"29-11-00-ZA1-97-003-002 (CTR1)":1,"29-18-00":3,"29-31-00":1,"29-32-00":1,"30-00":21,"30-11-00":8,"30-11-00-ZA5-21-003 (1.1)":1,"30-11-00-ZA5-21-004 (1.1)":1,"30-22-00":4,"30-22-01-010-30 (1.1)":6,"30-41-00":1,"30-41-00-ZA2-11-001":1,"30-41-00-ZA2-11-002 (LH)":1,"30-42-00":1,"30-42-00-ZA2-12-001 (RH)":1,"30-71-00":3,"31-00":8,"31-00-00":1,"31-31-00":3,"31-31-00-ZA2-23-001-H (M3131001 (FWD))":1,"31-31-00-ZA2-64-001-H (M3131002 (AFT))":1,"31-51-00":1,"31-61-00":12,"31-61-00-ZA2-11-006 (LEFT MFK)":1,"31-61-00-ZA2-11-011 (1.1)":1,"32-00":152,"32-00-00":3,"32-08-00":2,"32-11-00":10,"32-11-00-ZA7-31-054 (POS-05)":1,"32-11-00-ZA7-31-058 (POS-01)":1,"32-11-00-ZA7-31-059 (POS-02)":1,"32-11-00-ZA7-31-061 (POS-06)":1,"32-11-00-ZA7-41-056 (POS-08)":1,"32-11-00-ZA7-41-058 (POS-03)":2,"32-11-00-ZA7-41-059 (POS-04)":2,"32-11-00-ZA7-41-060 (POS-07)":1,"32-11-00-ZA7-41-061 (POS-08)":1,"32-12-00":10,"32-21-00":13,"32-21-00-ZA7-11-038-H (M3242149)":1,"32-22-00":11,"32-31-00":5,"32-31-01-01-010 (1.1)":1,"32-32-00":2,"32-35-00":1,"32-41-00":9,"32-41-00-ZA1-45-001-H-S":2,"32-42-00":14,"32-42-00-ZA1-13-001-H-S":2,"32-42-00-ZA1-14-001-H-S":1,"32-44-00":5,"32-45-00":109,"32-49-00":2,"32-50-00":2,"32-51-00":7,"32-61-00":2,"33-00":53,"33-00-00":3,"33-11-00":1,"33-13-00":2,"33-21-00":24,"33-22-00":4,"33-24-00":2,"33-25-00":2,"33-27-00":2,"33-28-00":1,"33-29-00":1,"33-31-00":12,"33-37-00":31,"33-41-00":2,"33-42-00":2,"33-43-00":12,"33-43-00-ZA6-43-001 (RIGHT)":1,"33-44-00":7,"33-45-00":8,"33-51-00":13,"34-00":22,"34-21-00":7,"34-21-00-ZA1-45-001-H-S":2,"34-21-00-ZA1-45-002-H (M3421003 [LEFT])":1,"34-21-00-ZA1-45-002-H-S":2,"34-31-00":3,"34-33-00":2,"34-42-00":3,"34-42-00-ZA1-18-005-H (M3442102 [RIGHT])":1,"34-42-00-ZA1-18-005-H-S":1,"34-55-00":1,"35-00":12,"35-11-00":17,"35-21-00":8,"35-31-00-ZA2-21-01-HTC (1.1-FLOOR STOWAGE-RH)":1,"35-31-00-ZA2-21-01-HTC (1.17)":1,"38-00":11,"38-00-00":2,"38-10-00":11,"38-11-00":2,"38-13-00":1,"38-14-00":3,"38-15-00":1,"38-15-00-ZA1-64-003 (1.1.1)":1,"38-30-00":8,"38-31-00":4,"38-31-00-ZA2-00-001 (L4F-1L)":1,"38-32-00":6,"38-33-00":1,"42-00":27,"42-00-00":10,"42-00-00-ZA1-14-010 (LEFT NO.1)":1,"42-00-00-ZA1-14-010 (LEFT NO.2)":1,"42-00-00-ZA1-17-006-H (GPM-L5 [E4220001M5] [LS1876":1,"42-21-00":18,"42-21-00-ZA1-14-007-H":1,"42-21-00-ZA1-17-007-H":1,"42-21-00-ZA2-12-001-H":1,"44-00":9,"44-11-00":7,"44-12-00":1,"44-14-00":2,"44-20-00":59,"44-21-00":1,"44-22-00":1,"44-26-00":89,"44-26-00-ZA-10-001 (SDB-12 JKL)":2,"44-26-00-ZA-10-001 (SDB-24 ABC)":1,"44-26-00-ZA-10-001 (SDB-26 DFH)":1,"44-26-00-ZA1-13-001-H-S":1,"44-26-00-ZA1-13-003 (M4421033 [DSU-3])":1,"44-26-00-ZA2-26-001 (MID RH)":1,"44-26-00-ZA2-26-002 (4 H)":1,"44-26-00-ZA2-26-004 (1.18)":1,"44-26-00-ZAA-26-001 (15 F)":1,"44-26-00-ZAA-26-001 (24 K)":1,"44-26-00-ZAA-26-001 (33 H)":1,"44-26-00-ZAA-26-001 (38 F)":1,"44-35-00 (1.1)":8,"45-00":5,"45-11-00":2,"46-00":23,"46-00-00":1,"46-10-00":1,"46-11-00":5,"46-12-00":19,"46-12-00-ZA1-17-003-H":1,"46-12-00-ZA1-53-001 (BLW AFT CARGO [CWLU])":1,"46-13-00":6,"47-00":12,"47-00-00":1,"47-11-00":16,"47-13-00":1,"47-14-00":1,"47-14-00-ZA1-92-002-HTC (1.1)":1,"47-16-00-ZA1-92-001 (1.1)":1,"47-21-00":1,"47-32-00":1,"49-00":18,"49-11-00":2,"49-15-00":1,"49-21-00":1,"49-31-00":1,"49-41-00":1,"49-61-00":1,"50-00":270,"50-00-00":15,"50-11-00":102,"50-21-00":91,"50-21-00-ZA1-10-941-155 (M5021519)":1,"50-21-00-ZA1-21-001-A-H (M5021101)":3,"50-21-00-ZA1-22-001-H-S (1.1)":2,"50-21-00-ZA1-22-002-A-H (M5021201)":1,"50-21-00-ZA1-22-003-A-H (M5021208)":1,"50-21-00-ZA1-22-004-A-H (M5021211)":1,"50-21-00-ZA1-22-004-B-H (M5021212)":2,"50-21-00-ZA1-22-006-A-H (M5021204)":1,"50-21-00-ZA1-22-008-A-H (M5021218)":1,"50-21-00-ZA1-51-001-B-H (M5021402)":1,"50-21-00-ZA1-51-002-D-H (M5021410)":1,"50-21-00-ZA1-52-001-H-S (1.1)":1,"50-21-00-ZA1-52-002-B-H (1L)":1,"50-21-00-ZA1-52-003-B-H (M5021504)":1,"50-21-00-ZA1-52-003-C-H (M5021509)":2,"50-21-00-ZA1-52-003-D-H (M5021510)":1,"50-60-00":16,"51-00":94,"51-03-00":2,"51-21-00":16,"52-00":57,"52-05-00":2,"52-09-00":1,"52-11-00":29,"52-11-00-ZA8-32-002-HTC (PED NO.1-RH)":1,"52-11-00-ZA8-43-002-HTC (PED NO.4-LH)":2,"52-21-00":2,"52-34-00":12,"52-34-00-ZA1-52-006 (1.1)":1,"52-35-00":8,"52-36-00":5,"52-40-00":11,"52-51-00":7,"52-53-00":5,"53-00":37,"53-00-00":5,"53-01-00":3,"53-05-00":1,"53-08-00":6,"53-10-50 (1.1)":2,"53-12-00":16,"53-12-00-ZA1-11-001-ARL":1,"53-36-00":1,"53-58-00":1,"53-66-00":1,"53-70-00 (1.1)":3,"53-90-00":6,"54-00":18,"54-00-00":3,"54-61-00":1,"54-62-00":6,"54-63-00":7,"54-65-00":1,"55-00":6,"55-05-00":1,"55-10-00":3,"55-16-00":1,"55-31-00":1,"56-00":15,"56-11-00":16,"56-21-00":13,"56-31-00":4,"57-00":35,"57-00-00":8,"57-05-00":3,"57-15-00":9,"57-25-00":5,"57-41-00":9,"57-51-00":7,"70-00":2,"71-00":20,"71-00-00":5,"71-10-00":7,"71-11-00":13,"71-11-00-ZA4-12-001":2,"71-11-00-ZA4-13-002":1,"71-11-00-ZA4-22-001":2,"71-11-01 (1.1)":1,"71-12-00-HTC":2,"71-12-01-01-50-RHOB (RIGHT ENGINE OUTBOARD)":1,"72-00":38,"72-00-00":8,"72-20-00":3,"72-21-00":5,"72-22-00":19,"72-25-00":3,"72-30-00":1,"72-50-00":2,"73-00":16,"73-20-00":1,"73-21-00":3,"73-34-00":1,"74-21-00":1,"75-00":9,"75-11-00":1,"75-20-00":1,"75-23-00":1,"75-24-00":3,"76-11-00":3,"77-00":10,"77-12-00":2,"77-31-00":1,"78-00":18,"78-11-00":1,"78-30-00":5,"78-31-00":11,"78-31-01 (1.1)":4,"78-34-00":1,"79-00":22,"79-00-00":2,"79-10-00":1,"80-11 -00":1,"APU APS5000":5,"APU APS5000->24-21-00-ZA3-15-001 (LH)":3,"APU APS5000->24-21-00-ZA3-15-002 (RH)":2,"APU APS5000->49-00":1,"APU APS5000->QEC":14,"APU APS5000->UNTRKD":1,"LH ENG - 787-8 (LH)":17,"LH ENG - 787-8 (LH) ->71-21-00":1,"LH ENG - 787-8 (LH) ->72 (1.1)":2,"LH ENG - 787-8 (LH) ->72-00":8,"LH ENG - 787-8 (LH) ->72-00 (1.1.1)":5,"LH ENG - 787-8 (LH) ->72-00-00":6,"LH ENG - 787-8 (LH) ->72-22-00-ZA9-03-001 (1.2)":1,"LH ENG - 787-8 (LH) ->72-22-00-ZA9-03-001 (1.6)":1,"LH ENG - 787-8 (LH) ->72-31 (1.1.1)":1,"LH ENG - 787-8 (LH) ->72-31-00-01-780 (1.1)":1,"LH ENG - 787-8 (LH) ->72-40-00":2,"LH ENG - 787-8 (LH) ->72-50-00":4,"LH ENG - 787-8 (LH) ->72-53-00-01-130":1,"LH ENG - 787-8 (LH) ->72-53-00-01-250":1,"LH ENG - 787-8 (LH) ->73 (1.1)":1,"LH ENG - 787-8 (LH) ->73-00":2,"LH ENG - 787-8 (LH) ->73-11-01 (1.1)":1,"LH ENG - 787-8 (LH) ->73-21-00-ZA9-03-001 (1.1)":1,"LH ENG - 787-8 (LH) ->73-21-11-01-250 (1.1.1)":1,"LH ENG - 787-8 (LH) ->73-22-00":1,"LH ENG - 787-8 (LH) ->74 (1.1)":1,"LH ENG - 787-8 (LH) ->75-00":2,"LH ENG - 787-8 (LH) ->75-33-15-01-250 (1.1.1)":1,"LH ENG - 787-8 (LH) ->77-32-10-01-060 (1.1.1)":1,"LH ENG - 787-8 (LH) ->78-31-00":1,"LH ENG - 787-8 (LH) ->79-32-00":2,"LH ENG - 787-8 (LH) ->QEC":43,"LH ENG - 787-8 (LH) ->QEC (1.1)":18,"LH ENG - 787-8 (LH) ->UNTRACKED":1,"RH ENG - 787-8 (RH)":17,"RH ENG - 787-8 (RH) ->71-21-00-ZA4-15-001 (1)":2,"RH ENG - 787-8 (RH) ->72-00":5,"RH ENG - 787-8 (RH) ->72-00 (1.1.1)":1,"RH ENG - 787-8 (RH) ->72-00-00":8,"RH ENG - 787-8 (RH) ->72-00-00-01-004 (1.1)":2,"RH ENG - 787-8 (RH) ->72-00-02-33-012A (1.1.1)":1,"RH ENG - 787-8 (RH) ->72-22-00":1,"RH ENG - 787-8 (RH) ->72-25-00-10-230 (1.1)":1,"RH ENG - 787-8 (RH) ->72-31-00-01-580":1,"RH ENG - 787-8 (RH) ->72-31-00-01-740":1,"RH ENG - 787-8 (RH) ->72-31-00-01-780 (1.1)":1,"RH ENG - 787-8 (RH) ->72-40-00":1,"RH ENG - 787-8 (RH) ->72-41-00-01-080":1,"RH ENG - 787-8 (RH) ->72-50-00":1,"RH ENG - 787-8 (RH) ->72-52 (1.1.1)":1,"RH ENG - 787-8 (RH) ->72-53-00-01-130":1,"RH ENG - 787-8 (RH) ->72-53-00-01-280":1,"RH ENG - 787-8 (RH) ->73-00":3,"RH ENG - 787-8 (RH) ->73-11-00-ZA9-03-001 (1.1)":2,"RH ENG - 787-8 (RH) ->73-11-01 (1.1)":2,"RH ENG - 787-8 (RH) ->73-21-00":1,"RH ENG - 787-8 (RH) ->73-21-00-ZA9-03-001 (1.1)":1,"RH ENG - 787-8 (RH) ->73-21-30-01-010A (1.1)":1,"RH ENG - 787-8 (RH) ->73-21-55-01-010 (1.1)":1,"RH ENG - 787-8 (RH) ->74 (1.1)":1,"RH ENG - 787-8 (RH) ->75 (1.1)":1,"RH ENG - 787-8 (RH) ->75-00":1,"RH ENG - 787-8 (RH) ->77-00":1,"RH ENG - 787-8 (RH) ->77-32-10-01-060 (1.1.1)":1,"RH ENG - 787-8 (RH) ->79-00":1,"RH ENG - 787-8 (RH) ->79-33-10-01-060 (1.1)":1,"RH ENG - 787-8 (RH) ->QEC":40,"RH ENG - 787-8 (RH) ->QEC (1.1)":10,"RH ENG - 787-8 (RH) ->UNTRKD (1.1)":1,"UNTRACKED":1},"Airbus":{"Unknown":17,"05 (1.1)":9,"05-2 (1.1.1)":23,"05-21 (1.1.1.1)":16,"05-21-90 (1.1.1.1.1)":1,"05-22 (1.1.1.1)":12,"05-23 (1.1.1.1)":1,"05-24 (1.1.1.1)":3,"05-25 (1.1.1.1)":19,"05-28 (1.1.1.1)":4,"05-5 (1.1.1)":103,"06 (1.1)":1,"10 (1.1)":1,"11 (1.1)":71,"11-23 (1.1.1)":9,"11-31 (1.1.1)":31,"11-34 (1.1.1)":18,"11-36 (1.1.1)":4,"12 (1.1)":4,"12-0 (1.1.1)":1,"12-3 (1.1.1)":1,"20 (1.1)":1,"20-1 (1.1.1)":2,"20-55 (1.1.1.1)":1,"21 (1.1)":3,"21-2 (1.1.1)":2,"21-21 (1.1.1.1)":2,"21-21-55 (1.1.1.1.1)":5,"21-22 (1.1.1.1)":1,"21-25 (1.1.1.1)":1,"21-28-42 (1.1.1.1.1)":1,"21-31 (1.1.1.1)":2,"21-31-35 (1.1.1.1.1)":2,"21-31-35-40-030A (102HL)":1,"21-31-58 (1.1.1.1.1)":3,"21-4 (1.1.1)":1,"21-42 (1.1.1.1)":2,"21-5 (1.1.1)":3,"21-52 (1.1.1.1)":1,"21-53 (1.1.1.1)":2,"21-53-51 (1.1.1.1.1)":1,"21-58-61 (1.1.1.1.1)":1,"21-59 (1.1.1.1)":7,"21-59-07 (1.1.1.1.1)":1,"21-59-55 (1.1.1.1.1)":10,"21-6 (1.1.1)":1,"21-72 (1.1.1.1)":1,"22 (1.1)":1,"23 (1.1)":1,"23-11 (1.1.1.1)":4,"23-11-33-01-010 (1RE1)":1,"23-11-33-01-010 (1RE2)":1,"23-12 (1.1.1.1)":2,"23-2 (1.1.1)":2,"23-25 (1.1.1.1)":1,"23-28 (1.1.1.1)":8,"23-33-56 (1.1.1.1.1)":1,"23-5 (1.1.1)":3,"23-51 (1.1.1.1)":2,"23-6 (1.1.1)":12,"23-61 (1.1.1.1)":1,"24 (1.1)":10,"24-00 (1.1.1)":3,"24-22 (1.1.1.1)":2,"24-4 (1.1.1)":5,"24-5 (1.1.1)":2,"24-7 (1.1.1)":1,"24-71 (1.1.1.1)":16,"24-71-57-01-010 (4383XZ)":1,"24-71-57-01-010 (4386XZ)":1,"24-71-57-01-070 (4321XZ)":1,"24-71-57-01-072 (4312XZ)":1,"24-71-57-04-010B (4559XZ)":1,"24-72 (1.1.1.1)":1,"24-74 (1.1.1.1)":2,"25 (1.1)":156,"25-0 (1.1.1)":24,"25-1 (1.1.1)":8,"25-11 (1.1.1.1)":21,"25-11-46 (3MS)":2,"25-13 (1.1.1.1)":46,"25-16 (1.1.1.1)":1,"25-2 (1.1.1)":35,"25-21 (1.1.1.1)":139,"25-21-44 (1.1.1.1.1)":31,"25-21-45 (1.1.1.1.1)":12,"25-21-46 (1.1.1.1.1)":27,"25-21-47 (1.1.1.1.1)":3,"25-21-48 (1.1.1.1.1)":2,"25-21-49 (1.1.1.1.1)":2,"25-22 (1.1.1.1)":39,"25-23 (1.1.1.1)":36,"25-24 (1.1.1.1)":16,"25-24-41 (1.1.1.1.1)":3,"25-25 (1.1.1.1)":6,"25-26 (1.1.1.1)":23,"25-27 (1.1.1.1)":9,"25-28 (1.1.1.1)":15,"25-3 (1.1.1)":101,"25-31 (1.1.1.1)":61,"25-35 (1.1.1.1)":21,"25-35-52-10B (223NL110.5)":1,"25-36 (1.1.1.1)":40,"25-36-43-20 (1.1.1.1.9)":1,"25-36-51 (1021NL181)":1,"25-36-71-30 (745NL120)":1,"25-4 (1.1.1)":43,"25-41 (1.1.1.1)":47,"25-44 (1.1.1.1)":1,"25-45 (1.1.1.1)":55,"25-5 (1.1.1)":1,"25-51 (1.1.1.1)":9,"25-6 (1.1.1)":17,"25-62 (1.1.1.1)":15,"25-62-47-01-010-HTC (7910MX)":1,"25-62-47-01-020-HTC (7911MX)":1,"25-62-47-03-020-HTC (7903MX)":1,"25-64 (1.1.1.1)":14,"25-65 (1.1.1.1)":11,"25-66 (1.1.1.1)":13,"25-67 (1.1.1.1)":2,"25-68 (1.1.1.1)":3,"25-8 (1.1.1)":1,"26 (1.1)":1,"26-1 (1.1.1)":8,"26-12 (1.1.1.1)":1,"26-12-16-01-160 (6WD2)":1,"26-15 (1.1.1.1)":1,"26-16-15 (1.1.1.1.1)":1,"26-2 (1.1.1)":1,"26-23 (1.1.1.1)":8,"26-23-31 (1.1.1.1.1)":1,"26-24 (1.1.1.1)":3,"26-24-61-21-040A (7526WE)":1,"26-25 (1.1.1.1)":1,"27 (1.1)":32,"27-1 (1.1.1)":12,"27-14 (1.1.1.1)":2,"27-14-53 (1.1.1.1.1)":6,"27-14-55 (1.1.1.1.1)":5,"27-2 (1.1.1)":1,"27-24 (1.1.1.1)":1,"27-24-53 (1.1.1.1.1)":1,"27-3 (1.1.1)":2,"27-34 (1.1.1.1)":1,"27-34-55-01 (1.1.1.1.1)":1,"27-4 (1.1.1)":3,"27-5 (1.1.1)":18,"27-51-34 (1.1.1.1.1)":1,"27-54 (1.1.1.1)":1,"27-54-51 (1.1.1.1.1)":2,"27-54-59 (1.1.1.1.1)":1,"27-6 (1.1.1)":4,"27-64 (1.1.1.1)":1,"27-64-53 (1.1.1.1.1)":8,"27-64-53-04-310 (4CL1)":1,"27-64-53-05-310 (6CL1)":1,"27-64-55 (1.1.1.1.1)":1,"27-8 (1.1.1)":6,"27-84 (1.1.1.1)":5,"27-84-52 (1.1.1.1.1)":1,"27-9 (1.1.1)":3,"27-90 (1.1.1.1)":1,"27-92-14-01-070 (5CP)":1,"27-92-16 (1.1.1.1.1)":1,"27-93-34 (1.1.1.1.1)":1,"27-94-34-01-010 (2CE2)":1,"28 (1.1)":2,"28-11 (1.1.1.1)":1,"28-18 (1.1.1.1)":3,"28-2 (1.1.1)":1,"28-21-51-01-040B-HTC (102QA1)":1,"28-21-72 (1.1.1.1.1)":1,"28-25 (1.1.1.1)":2,"28-25-25 (1.1.1.1.1)":3,"28-31-71 (1.1.1.1.1)":1,"28-5 (1.1.1)":1,"28-51 (1.1.1.1)":3,"29 (1.1)":8,"29-10 (1.1.1.1)":3,"29-11 (1.1.1.1)":4,"29-11-45 (1.1.1.1.1)":1,"29-11-56-01-010C\/020C-HTC (2JG2)":5,"29-11-68 (1.1.1.1.1)":1,"29-13 (1.1.1.1)":3,"29-13-45 (1.1.1.1.1)":3,"29-13-56-01-010C\/020C-HTC (2JY1)":1,"29-13-56-01-010C\/020C-HTC (2JY2)":1,"29-16-55 (1.1.1.1.1)":1,"29-21-35 (1.1.1.1.1)":1,"29-23-35-01-110A (2JJ)":1,"29-32 (1.1.1.1)":1,"29-33 (1.1.1.1)":1,"29-33-53 (1.1.1.1.1)":1,"29-33-55 (1.1.1.1.1)":1,"30 (1.1)":3,"30-11 (1.1.1.1)":1,"30-11-51 (1.1.1.1.1)":1,"30-3 (1.1.1)":1,"30-45 (1.1.1.1)":2,"30-7 (1.1.1)":1,"30-81 (1.1.1.1)":3,"30-81-15 (1.1.1.1.1)":2,"31 (1.1)":7,"31-1 (1.1.1)":3,"31-11 (1.1.1.1)":4,"31-19 (1.1.1.1)":1,"31-19-12-03-120C (211VM)":1,"31-19-12-06-070B (221VM)":1,"31-2 (1.1.1)":5,"31-5 (1.1.1)":3,"31-61 (1.1.1.1)":1,"31-61-25-01-010 (1WK22)":1,"31-62 (1.1.1.1)":1,"32 (1.1)":15,"32-0 (1.1.1)":2,"32-1 (1.1.1)":5,"32-11 (1.1.1.1)":10,"32-11-60-01-060-HTC (5500GM1) ->32-11-67 (1.1)":1,"32-11-60-01-060-HTC (5500GM1) ->32-11-69 (1.1)":2,"32-11-60-01-060-HTC (5500GM1) ->32-31-94 (1.1)":1,"32-11-60-01-060-HTC (5500GM1) ->32-41-62 (1.1)":13,"32-11-60-01-060-HTC (5500GM1) ->32-42-63 (1.1)":1,"32-11-60-01-060-HTC (5500GM1) ->32-42-63-01-010B (":1,"32-11-60-01-070-HTC (5500GM2) ->32-11-60 (1.1)":1,"32-11-60-01-070-HTC (5500GM2) ->32-11-62 (1.1)":1,"32-11-60-01-070-HTC (5500GM2) ->32-11-69 (1.1)":2,"32-11-60-01-070-HTC (5500GM2) ->32-11-73 (1.1)":1,"32-11-60-01-070-HTC (5500GM2) ->32-41-62 (1.1)":16,"32-11-60-01-070-HTC (5500GM2) ->32-42-63-01-010B (":4,"32-2 (1.1.1)":4,"32-21 (1.1.1.1)":5,"32-31-66 (1.1.1.1.1)":1,"32-4 (1.1.1)":4,"32-41-64 (1.1.1.1.1)":1,"32-42 (1.1.1.1)":1,"32-42-63 (1.1.1.1.1)":1,"32-5 (1.1.1)":1,"32-51 (1.1.1.1)":2,"32-51-33 (1.1.1.1.1)":1,"32-51-51 (1.1.1.1.1)":1,"33 (1.1)":11,"33-12 (1.1.1.1)":2,"33-13 (1.1.1.1)":2,"33-2 (1.1.1)":4,"33-21 (1.1.1.1)":4,"33-23 (1.1.1.1)":14,"33-3 (1.1.1)":3,"33-34 (1.1.1.1)":1,"33-4 (1.1.1)":1,"33-41 (1.1.1.1)":1,"33-41-13-01-020B (17LA)":2,"33-42 (1.1.1.1)":2,"33-43 (1.1.1.1)":2,"33-43-13-01-010B (24LC)":1,"33-44 (1.1.1.1)":1,"33-46 (1.1.1.1)":4,"33-47 (1.1.1.1)":17,"33-47-32-01-040A (3LY1)":1,"33-47-32-01-040A (3LY2)":1,"33-48 (1.1.1.1)":3,"33-5 (1.1.1)":2,"33-51 (1.1.1.1)":10,"34 (1.1)":4,"34-1 (1.1.1)":1,"34-11 (1.1.1.1)":3,"34-12-34-01-010A (1FP1)":1,"34-22 (1.1.1.1)":1,"34-22-25-01-030 (10FC1)":2,"34-42 (1.1.1.1)":5,"34-42-11-01-050 (6SA1)":1,"34-5 (1.1.1)":1,"34-51 (1.1.1.1)":9,"34-53 (1.1.1.1)":2,"34-7 (1.1.1)":2,"34-71 (1.1.1.1)":9,"34-71-33-01-030 (7SE1)":1,"35 (1.1)":2,"35-1 (1.1.1)":4,"35-11 (1.1.1.1)":5,"35-11-56 (1.1.1.1.1)":13,"35-12 (1.1.1.1)":3,"35-2 (1.1.1)":4,"35-21 (1.1.1.1)":4,"35-23 (1.1.1.1)":1,"35-3 (1.1.1)":14,"35-32 (1.1.1.1)":1,"35-32-61-OC (6001HP3)":1,"35-32-61-OC (6008HP1)":1,"36 (1.1)":2,"36-1 (1.1.1)":3,"36-11 (1.1.1.1)":2,"36-11-34 (1.1.1.1.1)":1,"36-11-49 (1.1.1.1.1)":1,"36-11-53 (1.1.1.1.1)":1,"36-11-53-01-100 (15HA2)":1,"36-11-63-01-090 (13HA1)":1,"36-11-63-01-180 (13HA2)":1,"36-2 (1.1.1)":3,"38 (1.1)":4,"38-1 (1.1.1)":15,"38-11 (1.1.1.1)":2,"38-12 (1.1.1.1)":11,"38-12-25-55-01-130 (120MB)":1,"38-13 (1.1.1.1)":9,"38-14 (1.1.1.1)":10,"38-3 (1.1.1)":8,"38-31 (1.1.1.1)":20,"38-32 (1.1.1.1)":4,"38-4 (1.1.1)":1,"38-5 (1.1.1)":8,"38-51 (1.1.1.1)":3,"42 (1.1)":1,"42-41 (1.1.1.1)":2,"44 (1.1)":14,"44-1 (1.1.1)":11,"44-11 (1.1.1.1)":17,"44-2 (1.1.1)":112,"44-21 (1.1.1.1)":30,"44-22 (1.1.1.1)":6,"44-24-03-010 (4 C)":1,"44-28 (1.1.1.1)":2,"44-28-61-010 (120MK102)":1,"44-3 (1.1.1)":5,"44-33 (1.1.1.1)":8,"44-34 (1.1.1.1)":2,"44-5 (1.1.1)":2,"44-52 (1.1.1.1)":4,"46 (1.1)":4,"46-1 (1.1.1)":1,"46-12 (1.1.1.1)":1,"46-12-34 (1.1.1.1.1)":1,"46-12-34-01-020 (102TC4)":1,"46-12-35 (1.1.1.1.1)":2,"46-26 (1.1.1.1)":5,"47 (1.1)":1,"47-1 (1.1.1)":1,"47-10 (1.1.1.1)":3,"47-10-62 (1.1.1.1.1)":1,"49 (1.1)":2,"49-11-11 (1.1.1.1.1)":1,"49-11-11-01-04A (5100KB) ->49-24 (1.1.1)":1,"49-11-11-01-04A (5100KB) ->49-24-90-05-005A (1.1.1":1,"49-11-11-01-04A (5100KB) ->49-24-90-17-005A (1.1.1":1,"49-11-11-01-04A (5100KB) ->QEC (1.1)":4,"49-12 (1.1.1.1)":1,"49-13 (1.1.1.1)":1,"49-16 (1.1.1.1)":1,"49-42-54-10-190B (21KA)":2,"49-81 (1.1.1.1)":1,"50 (1.1)":66,"50-1 (1.1.1)":64,"50-13 (1.1.1.1)":200,"50-13-67 (1.1.1.1.1)":11,"50-2 (1.1.1)":22,"50-23 (1.1.1.1)":74,"50-23-19 [PDU, SPRING LOADED] (1508MY11)":1,"50-23-19 [PDU, SPRING LOADED] (1508MY12)":1,"50-23-19 [PDU, SPRING LOADED] (1509MY11)":1,"50-23-19 [PDU, SPRING LOADED] (1551MY11)":1,"50-23-63 (1.1.1.1.1)":30,"51 (1.1)":21,"51-1 (1.1.1)":1,"51-4 (1.1.1)":3,"51-7 (1.1.1)":7,"52 (1.1)":14,"52-1 (1.1.1)":15,"52-11 (1.1.1.1)":13,"52-12 (1.1.1.1)":10,"52-13 (1.1.1.1)":5,"52-3 (1.1.1)":8,"52-33 (1.1.1.1)":17,"52-36 (1.1.1.1)":5,"52-36-63 (1.1.1.1.1)":8,"52-4 (1.1.1)":13,"52-41 (1.1.1.1)":15,"52-5 (1.1.1)":4,"52-51 (1.1.1.1)":13,"52-71 (1.1.1.1)":2,"52-8 (1.1.1)":2,"52-81 (1.1.1.1)":2,"52-82 (1.1.1.1)":2,"53 (1.1)":42,"53-0 (1.1.1)":5,"53-1 (1.1.1)":2,"53-11 (1.1.1.1)":1,"53-15 (1.1.1.1)":1,"53-15-73 (1.1.1.1.1)":2,"53-19 (1.1.1.1)":1,"53-2 (1.1.1)":12,"53-3 (1.1.1)":16,"53-31 (1.1.1.1)":1,"53-35-75 (1.1.1.1.1)":1,"53-4 (1.1.1)":15,"53-41 (1.1.1.1)":3,"53-5 (1.1.1)":1,"53-51 (1.1.1.1)":1,"54 (1.1)":5,"54-1 (1.1.1)":2,"54-3 (1.1.1)":2,"54-5 (1.1.1)":2,"54-50 (1.1.1.1)":1,"55 (1.1)":3,"55-1 (1.1.1)":6,"55-11 (1.1.1.1)":2,"55-12 (1.1.1.1)":2,"55-16 (1.1.1.1)":4,"55-2 (1.1.1)":1,"56 (1.1)":1,"56-2 (1.1.1)":10,"56-3 (1.1.1)":3,"56-31 (1.1.1.1)":3,"57 (1.1)":43,"57-1 (1.1.1)":4,"57-19 (1.1.1.1)":1,"57-2 (1.1.1)":20,"57-24 (1.1.1.1)":1,"57-3 (1.1.1)":5,"57-4 (1.1.1)":13,"57-41 (1.1.1.1)":4,"57-43 (1.1.1.1)":1,"57-44 (1.1.1.1)":9,"57-44-61 (1.1.1.1.1)":1,"57-46 (1.1.1.1)":23,"57-5 (1.1.1)":15,"57-51 (1.1.1.1)":7,"57-53 (1.1.1.1)":2,"57-54 (1.1.1.1)":1,"57-56 (1.1.1.1)":3,"57-57 (1.1.1.1)":8,"57-6 (1.1.1)":1,"57-61 (1.1.1.1)":2,"57-71 (1.1.1.1)":2,"70 (1.1)":1,"71 (1.1)":6,"71-00 (1.1.1.1)":2,"71-1 (1.1.1)":6,"71-13 (1.1.1.1)":8,"71-13-63 (1.1.1.1.1)":1,"71-13-64 (1.1.1.1.1)":1,"71-22 (1.1.1.1)":1,"71-40-62 (1.1.1.1.1)":1,"71-60-61 (1.1.1.1.1)":10,"71-71 (1.1.1.1)":1,"71-71-63 (1.1.1.1.1)":3,"72 (1.1)":5,"72-00 (1.1.1)":8,"72-2 (1.1.1)":1,"72-31-62 (1.1.1.1.1)":1,"72-33 (1.1.1.1)":1,"72-35 (1.1.1.1)":3,"72-35-63 (1.1.1.1.1)":2,"72-35-64 (1.1.1.1.1)":1,"72-35-65 (1.1.1.1.1)":1,"73 (1.1)":4,"73-33 (1.1.1.1)":1,"75-24 (1.1.1.1)":5,"77 (1.1)":2,"78 (1.1)":8,"78-3 (1.1.1)":3,"78-32 (1.1.1.1)":9,"78-32-61 (1.1.1.1.1)":1,"78-36 (1.1.1.1)":1,"79 (1.1)":2,"79-21 (1.1.1.1)":1,"79-34 (1.1.1.1)":1,"91-13 (1.1.1.1)":1,"91-14 (1.1.1.1)":1,"91-15 (1.1.1.1)":2,"92 (1.1)":1,"CMM 21-58-51-630 (202HH1)":1,"CMM27-52-40-090 (81CV)":1,"CMM27-54-20-030 (24CV)":1,"LH ENG - A350-900\/1000 (LH)":2,"LH ENG - A350-900\/1000 (LH) ->11 (1.1)":4,"LH ENG - A350-900\/1000 (LH) ->24 (1.1)":1,"LH ENG - A350-900\/1000 (LH) ->36 (1.1)":4,"LH ENG - A350-900\/1000 (LH) ->72 (1.1)":2,"LH ENG - A350-900\/1000 (LH) ->72-00 (1.1.1)":1,"LH ENG - A350-900\/1000 (LH) ->72-35 (1.1.1)":2,"LH ENG - A350-900\/1000 (LH) ->72-41 (1.1.1)":3,"LH ENG - A350-900\/1000 (LH) ->73 (1.1)":4,"LH ENG - A350-900\/1000 (LH) ->75-33-15-02-250 (1.1":1,"LH ENG - A350-900\/1000 (LH) ->80 (1.1)":2,"LH ENG - A350-900\/1000 (LH) ->80-11 (1.1.1)":2,"LH ENG - A350-900\/1000 (LH) ->QEC (1.1)":4,"LH ENG - A350-900\/1000 (LH) ->UNTRKD (1.1)":1,"NOSE LANDING GEAR ASSY (5500GN) ->32-21-01 (1.1)":2,"NOSE LANDING GEAR ASSY (5500GN) ->32-41-61 (1.1)":3,"RH ENG - A350-900\/1000 (RH) ->36-11-54-01-010 (1.1":1,"RH ENG - A350-900\/1000 (RH) ->72-35 (1.1.1)":2,"RH ENG - A350-900\/1000 (RH) ->72-41 (1.1.1)":1,"RH ENG - A350-900\/1000 (RH) ->72-51 (1.1.1)":1,"RH ENG - A350-900\/1000 (RH) ->73-21-11-01-250A (40":1,"RH ENG - A350-900\/1000 (RH) ->74-21-12 (1.1.1.1)":1,"RH ENG - A350-900\/1000 (RH) ->75 (1.1)":1,"RH ENG - A350-900\/1000 (RH) ->77 (1.1)":1,"RH ENG - A350-900\/1000 (RH) ->78-11-61-01-070A (1.":1,"RH ENG - A350-900\/1000 (RH) ->QEC (1.1)":8,"RH ENG - A350-900\/1000 (RH) ->UNTRKD (1.1)":1,"UNTK (1.1)":2},"Q400":{"Unknown":14,"05":15,"05-41":1,"05-42":1,"05-50":3,"06":20,"06-10":2,"11":6,"11-00 (1.1)":2,"11-22":1,"11-24":1,"11-32":1,"11-35":1,"12":2,"20 (1.1)":9,"21":8,"21-22":2,"21-22-16-01-010D":1,"21-31":7,"21-31-06-01-010":1,"21-51":8,"21-51-01-01-010B-HTC":1,"21-52":3,"21-52-00-01-040D":1,"21-61":4,"21-61-01-01-010G":1,"22-10-00-01-020":2,"22-11":2,"22-11-01-01-010E":1,"22-11-11-01-010A":1,"23":5,"23-11":3,"23-11-01-01-010 (2)":1,"23-12":5,"23-31":3,"23-35":6,"23-35-01-01-010A":1,"23-51":8,"23-71":1,"23-81":8,"23-81-01-01-010K (Cockpit, Center Console #1)":1,"24":8,"24-00":2,"24-20":1,"24-21-06-01-010 (2)":1,"24-21-21-01-200":1,"24-31":6,"24-32":8,"25":35,"25-00":2,"25-10":1,"25-11":2,"25-12":1,"25-13":1,"25-14":1,"25-15":3,"25-16":9,"25-20":6,"25-22":10,"25-23":3,"25-24":12,"25-25":10,"25-26":13,"25-27":1,"25-28":1,"25-31":3,"25-32":5,"25-33":3,"25-34":1,"25-35":4,"25-41":12,"25-51":3,"25-52":9,"25-61":1,"25-62":10,"25-63":1,"26":2,"26-00":1,"26-12":1,"26-12-06-01-005B-HTC (FWD)":1,"26-13":1,"26-22-01-01-05-HTC":1,"26-24":1,"27":1,"27-00":1,"27-10":1,"27-14":1,"27-31":1,"27-33":3,"27-33-01-01-010B (1)":1,"27-50":3,"27-52":3,"27-52-16-05-020A (2)":1,"27-54":6,"27-62-01-01-010B (1)":1,"27-62-01-01-010B (3)":1,"27-62-01-01-010B (4)":1,"27-63":1,"28":1,"28-00":1,"28-20":1,"28-23":1,"28-24":4,"28-24-31-01-020 (1.2)":1,"28-40":2,"29":6,"29-00":4,"29-11":9,"29-11-01-01-010B (RH)":5,"29-11-61-01-010":1,"29-12":4,"29-12-21-01-010B":3,"30":10,"30-10":4,"30-11":10,"30-11-01-01-010":1,"30-11-16-01-060D (2)":1,"30-21":4,"30-41":4,"30-42":3,"30-61":3,"30-80":2,"30-80-00-01-010D (1)":2,"31":3,"31-11":1,"31-12":1,"31-14":2,"31-41":2,"31-51":1,"31-53":1,"31-61":4,"31-61-01-01-010H (Zone # 211(Display unit ED))":1,"31-61-01-01-010H (Zone # 211(Display unit MFD #1))":1,"32":53,"32-00":9,"32-11":39,"32-11-00-01-030C-HTC (LH)":1,"32-11-00-01-030C-HTC (RH)":1,"32-11-01-01-100 (RH)":1,"32-12":7,"32-12-01-01-005 (Aft MLG Door Assy  I\/B(R Nacelle)":1,"32-12-01-01-010 (Aft MLG Door Assy Inbd(L Nacelle)":1,"32-21":10,"32-21-00-01-001-HTC":1,"32-21-00-01-010K-HTC":4,"32-21-00-01-080B-HTC":1,"32-21-01-05-230A":3,"32-22":4,"32-22-00-05-020":1,"32-31":4,"32-31-11-01-010-HTC (LH)":1,"32-31-11-01-010-HTC (RH)":1,"32-31-46-01-010D-HTC":1,"32-34":4,"32-40":8,"32-41":94,"32-42":4,"32-42-01-01-010B NEW (LH.2)":1,"32-44":4,"32-44-06-01-010":1,"32-46":3,"32-46-01-01-010":1,"32-51":3,"32-61":3,"33":6,"33-24":1,"33-25":1,"33-31":1,"33-32":2,"33-41":13,"33-42":4,"33-44-06-01-010A (Lower Anti-Collision Light)":2,"33-45":1,"33-45-01-01-020":1,"33-51":4,"33-51-01-01-010-HTC (Zone 235BZ(Cabin Headliner #1":1,"34":3,"34-11":3,"34-12":6,"34-12-16-05-020 (Zone 211(Cockpit, Instrument Pane":2,"34-21":9,"34-21-00-01-055B (RIGHT WING TIP)":1,"34-41":4,"34-41-01-01A-010 (Front Fuse)":1,"34-43":5,"34-44":1,"34-44-02-15-080 (2)":1,"34-51":3,"34-54":3,"34-61":7,"35":7,"35-10":13,"35-11":5,"35-11-06-01-010-HTC (OBSERVER)":2,"35-20 (1.1)":4,"35-21 (1.1)":3,"35-21-00-20-05 (1.1.1)":1,"35-21-00-20-05B (1.1.1)":1,"35-31-01-05-020-HTC (AFT RH  DOGHOUSE)":1,"35-31-HTC":4,"35-36-HTC":1,"35-40 (1.1)":2,"36":3,"36-11":8,"38":2,"38-20":4,"38-23":4,"38-31":1,"38-31-01-01-01 (FWD)":1,"49":6,"49-00":6,"49-22":2,"49-30":3,"49-30-04-01-010X (POS1)":1,"49-50":10,"49-60":2,"51 (1.1)":1,"51-21 (1.1.1)":3,"51-25 (1.1.1)":3,"51-80 (1.1.1)":2,"52":12,"52-10":4,"52-11":8,"52-12":3,"52-13":2,"52-21":5,"52-23":2,"52-31":9,"52-32":4,"52-40":2,"52-41":1,"52-42":2,"52-43":1,"52-44":2,"52-51":4,"52-70":1,"53":6,"53-00":1,"53-10":1,"53-11":1,"53-12":2,"53-20":4,"53-23":1,"53-30":1,"53-40":3,"53-50":1,"54":1,"54-31":2,"54-32":1,"55-13-00-01-020D":6,"55-13-00-01-030D":1,"55-13-00-01-050D":2,"55-13-00-01-060D":3,"55-33-00-01-010D":2,"56":3,"56-00":1,"56-10":7,"56-10-00-01-020D":1,"56-20":1,"57":6,"57-00":4,"57-11":1,"57-13":2,"57-13-00-01-020A (1(LH))":1,"57-13-00-01-030A (RH)":2,"57-20":1,"57-23":15,"57-23-00-01-100A (1(Left Wing Leading Edge))":1,"57-23-00-01-150A (1(Right Wing Leading Edge))":1,"57-23-00-01-190A (1(Right Wing Leading Edge))":2,"57-23-00-01-280A":1,"57-23-00-01-290A":2,"57-24":1,"57-25":1,"57-32":2,"57-51":1,"57-52 (1.1)":1,"57-53":1,"57-54":1,"61":9,"61-10":15,"61-20":3,"71":8,"71-10":19,"71-10-00-01-030A":1,"71-10-00-01-300J (1.1)":2,"71-10-00-05-300J (1.1)":1,"71-20":1,"71-21":11,"71-21-00-01-010A-HTC (LH ENG FWD 1)":2,"71-21-00-01-010A-HTC (LH ENG FWD 2)":2,"71-21-00-01-020A-HTC (RH ENG FWD 2)":1,"71-21-00-01-030-HTC (RH ENG TOP)":1,"71-21-00-01-040-HTC (LH ENG AFT 1)":1,"71-22":1,"71-50":1,"71-61":2,"71-71":1,"72":2,"72-00":8,"72-10":1,"72-40":1,"73":1,"74-11":1,"75":1,"75-31":1,"78":2,"78-10":5,"78-10-01-01-005":1,"79":1,"79-21":4,"79-22":1,"79-35":1,"APS1000 APU":22,"APS1000 APU->49-11 (1.1)":4,"APS1000 APU->49-11-00-01-020A-HTC (APU DC STARTER)":1,"APS1000 APU->49-20":5,"APS1000 APU->49-20-01-01-150":1,"APS1000 APU->49-24":2,"APS1000 APU->49-40 (1.1)":2,"APS1000 APU->QEC (1.1)":3,"PROP150A (LT)":13,"PROP150A (LT) ->61":3,"PROP150A (LT) ->61-00 (1.1)":4,"PROP150A (LT) ->61-10":23,"PROP150A (LT) ->61-10-06-01-001-HTC":1,"PROP150A (LT) ->61-10-11-01-001 (1)":1,"PROP150A (LT) ->61-20":3,"PROP150A (LT) ->61-20-36-01-005":1,"PROP150A (RT)":14,"PROP150A (RT) ->61":1,"PROP150A (RT) ->61-00 (1.1)":1,"PROP150A (RT) ->61-10":16,"PROP150A (RT) ->61-10-01-01-001-HTC (1)":1,"PROP150A (RT) ->61-10-01-01-001-HTC (2)":1,"PROP150A (RT) ->61-10-01-01-001-HTC (3)":1,"PROP150A (RT) ->61-10-01-01-001-HTC (5)":2,"PROP150A (RT) ->61-10-01-01-001-HTC (6)":1,"PROP150A (RT) ->61-10-06-01-001-HTC":6,"PROP150A (RT) ->61-20":2,"PROP150A (RT) ->61-20-36-01-005":2,"PROP150A (RT) ->UNTRKD (1.1)":2,"PW150A ENGINE-HTC (LH)":17,"PW150A ENGINE-HTC (LH) ->24":2,"PW150A ENGINE-HTC (LH) ->24-21-01-01-020B-HTC (AC ":1,"PW150A ENGINE-HTC (LH) ->24-31-01-01-070A-HTC (1.2":1,"PW150A ENGINE-HTC (LH) ->24-31-01-01-070A-HTC (DC ":2,"PW150A ENGINE-HTC (LH) ->72-00":3,"PW150A ENGINE-HTC (LH) ->72-31-00-03-150B":1,"PW150A ENGINE-HTC (LH) ->72-34-00-03-220":1,"PW150A ENGINE-HTC (LH) ->72-41":1,"PW150A ENGINE-HTC (LH) ->73":2,"PW150A ENGINE-HTC (LH) ->73-11-00-11-010":1,"PW150A ENGINE-HTC (LH) ->73-21":3,"PW150A ENGINE-HTC (LH) ->73-21-00-03-010":1,"PW150A ENGINE-HTC (LH) ->73-21-00-05-010":1,"PW150A ENGINE-HTC (LH) ->75-31":1,"PW150A ENGINE-HTC (LH) ->77-11":2,"PW150A ENGINE-HTC (LH) ->QEC (1.1)":1,"PW150A ENGINE-HTC (RH)":14,"PW150A ENGINE-HTC (RH) ->72":1,"PW150A ENGINE-HTC (RH) ->72-00":2,"PW150A ENGINE-HTC (RH) ->72-11-00-01-001":1,"PW150A ENGINE-HTC (RH) ->72-21-00-07-001":1,"PW150A ENGINE-HTC (RH) ->72-32-00-17-230":1,"PW150A ENGINE-HTC (RH) ->72-34":2,"PW150A ENGINE-HTC (RH) ->72-34-00-03-220":2,"PW150A ENGINE-HTC (RH) ->72-34-00-09-001":2,"PW150A ENGINE-HTC (RH) ->72-41":1,"PW150A ENGINE-HTC (RH) ->72-41-00-06-001":1,"PW150A ENGINE-HTC (RH) ->72-51-00-02-070":1,"PW150A ENGINE-HTC (RH) ->72-53-00-03-040":3,"PW150A ENGINE-HTC (RH) ->72-53-00-04-001":2,"PW150A ENGINE-HTC (RH) ->72-53-00-04-040":1,"PW150A ENGINE-HTC (RH) ->73":1,"PW150A ENGINE-HTC (RH) ->73-11":2,"PW150A ENGINE-HTC (RH) ->73-12":1,"PW150A ENGINE-HTC (RH) ->73-21-00-03-010":2,"PW150A ENGINE-HTC (RH) ->73-31-11-01-010 (1.1.1.1)":1,"PW150A ENGINE-HTC (RH) ->75-31":2,"PW150A ENGINE-HTC (RH) ->75-31-00-04-010":1,"PW150A ENGINE-HTC (RH) ->79":1,"PW150A ENGINE-HTC (RH) ->79-22":1,"PW150A ENGINE-HTC (RH) ->QEC (1.1)":3,"QEC (1.1)":1}}}