{
  "registration": "ET-ASA",
  "oem_model": "Q400",
  "fleet": "Bombardier Q400 Fleet",
  "total_defects": 27,
  "defects": [
    {
      "ac_registration": "ET-ASA",
      "oem_model": "Q400",
      "fault_name": "FWD PASSENGER WALK WAY SIDE FLOOR PANEL SUPPORT BRACKET BROKEN.",
      "fault_id": "TSFN800B3QT4",
      "tsfn": "TSFN800B3QT4",
      "config_position": "53-20",
      "due_date": "04-OCT-2023 23:59 EAT",
      "inventory": "53-20 - FORWARD CENTER FUSELAGE (X19.775 - X234.475)",
      "found_on_date": "08-JUL-2023 16:55 EAT",
      "found_on_flight": "",
      "severity": "NEFMEL",
      "status": "DEFER",
      "failure_type": "",
      "fault_priority": "",
      "deferral_class": "NEFMEL D",
      "deferral_reference": "DECISION TREE, NEFMEL",
      "work_types": "",
      "driving_task_name": "",
      "driving_task_id": "",
      "operational_restrictions": "",
      "etops_significant": "",
      "work_package_name": "audit",
      "work_package_id": "TSFN800FAJRU",
      "work_package_no": "",
      "ro": "",
      "material_availability": "N/A",
      "scraped_at": "2025-12-12 12:12:27"
    },
    {
      "ac_registration": "ET-ASA",
      "oem_model": "Q400",
      "fault_name": "ALL OVERHEAD STOWAGE BIN NEEDS PAINT RECONDITIONING.",
      "fault_id": "TSFN800CB403",
      "tsfn": "TSFN800CB403",
      "config_position": "25-51",
      "due_date": "01-JUL-2024 23:59 EAT",
      "inventory": "25-51 - BAGGAGE COMPARTMENTS",
      "found_on_date": "03-MAR-2024 18:52 EAT",
      "found_on_flight": "ET177",
      "severity": "MINR-WD",
      "status": "NFF",
      "failure_type": "",
      "fault_priority": "",
      "deferral_class": "NEFMEL D",
      "deferral_reference": "DECISION TREE 25-20",
      "work_types": "",
      "driving_task_name": "",
      "driving_task_id": "",
      "operational_restrictions": "",
      "etops_significant": "",
      "work_package_name": "audit",
      "work_package_id": "TSFN800FAJRU",
      "work_package_no": "",
      "ro": "",
      "material_availability": "N/A",
      "scraped_at": "2025-12-12 12:12:27"
    },
    {
      "ac_registration": "ET-ASA",
      "oem_model": "Q400",
      "fault_name": "RIGHT SIDE FLARE LIGHT INOP.",
      "fault_id": "TSFN800CZ9N1",
      "tsfn": "TSFN800CZ9N1",
      "config_position": "33-41",
      "due_date": "19-JUL-2024 23:59 EAT",
      "inventory": "33-41 - EXTERIOR LIGHTS",
      "found_on_date": "09-JUL-2024 15:48 EAT",
      "found_on_flight": "ET181",
      "severity": "MINR-WD",
      "status": "DEFER",
      "failure_type": "",
      "fault_priority": "",
      "deferral_class": "MEL C",
      "deferral_reference": "33-40-7",
      "work_types": "",
      "driving_task_name": "",
      "driving_task_id": "",
      "operational_restrictions": "",
      "etops_significant": "",
      "work_package_name": "audit",
      "work_package_id": "TSFN800FAJRU",
      "work_package_no": "",
      "ro": "",
      "material_availability": "N/A",
      "scraped_at": "2025-12-12 12:12:27"
    },
    {
      "ac_registration": "ET-ASA",
      "oem_model": "Q400",
      "fault_name": "PERFORM RE TORQUE",
      "fault_id": "TSFN800DLXZ4",
      "tsfn": "TSFN800DLXZ4",
      "config_position": "61-10",
      "due_date": "09-NOV-2024 23:59 EAT",
      "inventory": "61-10 - PROPELLER",
      "found_on_date": "08-NOV-2024 06:06 EAT",
      "found_on_flight": "",
      "severity": "MINR-WD",
      "status": "DEFER",
      "failure_type": "",
      "fault_priority": "",
      "deferral_class": "OTHER",
      "deferral_reference": "61-10",
      "work_types": "",
      "driving_task_name": "",
      "driving_task_id": "",
      "operational_restrictions": "",
      "etops_significant": "",
      "work_package_name": "audit",
      "work_package_id": "TSFN800FAJRU",
      "work_package_no": "",
      "ro": "",
      "material_availability": "N/A",
      "scraped_at": "2025-12-12 12:12:27"
    },
    {
      "ac_registration": "ET-ASA",
      "oem_model": "Q400",
      "fault_name": "ICE-PROTECTION PANEL ROBBED FOR ET-AXW",
      "fault_id": "TSFN800B3TS0",
      "tsfn": "TSFN800B3TS0",
      "config_position": "21",
      "due_date": "07-OCT-2023 23:59 EAT(10-DEC-2024 23:59 EAT)",
      "inventory": "21 - AIR CONDITIONING",
      "found_on_date": "09-JUL-2023 09:17 EAT",
      "found_on_flight": "",
      "severity": "TLI",
      "status": "DEFER",
      "failure_type": "",
      "fault_priority": "",
      "deferral_class": "TLI-90D",
      "deferral_reference": "31",
      "work_types": "",
      "driving_task_name": "ICE-PROTECTION PANEL ROBBED FOR ET-AXW",
      "driving_task_id": "TSFN800B3TS0",
      "operational_restrictions": "",
      "etops_significant": "",
      "work_package_name": "",
      "work_package_id": "",
      "work_package_no": "",
      "ro": "",
      "material_availability": "N/A",
      "scraped_at": "2025-12-12 12:12:27"
    },
    {
      "ac_registration": "ET-ASA",
      "oem_model": "Q400",
      "fault_name": "#2 PEC ROBBED FOR ET-AXW",
      "fault_id": "TSFN800B4HUV",
      "tsfn": "TSFN800B4HUV",
      "config_position": "PROP150A (RT) ->61-20",
      "due_date": "11-OCT-2023 23:59 EAT(14-DEC-2024 23:59 EAT)",
      "inventory": "61-20 - PROPELLER CONTROLLING",
      "found_on_date": "13-JUL-2023 15:06 EAT",
      "found_on_flight": "",
      "severity": "TLI",
      "status": "DEFER",
      "failure_type": "",
      "fault_priority": "",
      "deferral_class": "TLI-90D",
      "deferral_reference": "61",
      "work_types": "",
      "driving_task_name": "#2 PEC ROBBED FOR ET-AXW",
      "driving_task_id": "TSFN800B4HUV",
      "operational_restrictions": "",
      "etops_significant": "",
      "work_package_name": "",
      "work_package_id": "",
      "work_package_no": "",
      "ro": "",
      "material_availability": "N/A",
      "scraped_at": "2025-12-12 12:12:27"
    },
    {
      "ac_registration": "ET-ASA",
      "oem_model": "Q400",
      "fault_name": "#4 MLG WHEEL SPEED TRANSDUCER IS ROBED TO ET-AXF",
      "fault_id": "TSFN800B3FGR",
      "tsfn": "TSFN800B3FGR",
      "config_position": "32-41",
      "due_date": "05-OCT-2023 23:59 EAT(28-DEC-2024 23:59 EAT)",
      "inventory": "32-41 - WHEELS",
      "found_on_date": "07-JUL-2023 02:29 EAT",
      "found_on_flight": "",
      "severity": "TLI",
      "status": "DEFER",
      "failure_type": "",
      "fault_priority": "",
      "deferral_class": "TLI-90D",
      "deferral_reference": "32",
      "work_types": "",
      "driving_task_name": "#4 MLG WHEEL SPEED TRANSDUCER IS ROBED TO ET-AXF",
      "driving_task_id": "TSFN800B3FGR",
      "operational_restrictions": "",
      "etops_significant": "",
      "work_package_name": "",
      "work_package_id": "",
      "work_package_no": "",
      "ro": "",
      "material_availability": "N/A",
      "scraped_at": "2025-12-12 12:12:27"
    },
    {
      "ac_registration": "ET-ASA",
      "oem_model": "Q400",
      "fault_name": "ERROR",
      "fault_id": "TSFN800DQX34",
      "tsfn": "TSFN800DQX34",
      "config_position": "PW150A ENGINE-HTC (LH) ->72-00",
      "due_date": "-476.01 HOUR05-SEP-2025 12:09 EAT",
      "inventory": "72-00 - ENGINE",
      "found_on_date": "28-NOV-2024 03:07 EAT",
      "found_on_flight": "",
      "severity": "TLI",
      "status": "NFF",
      "failure_type": "CT",
      "fault_priority": "",
      "deferral_class": "TLI-ENG",
      "deferral_reference": "72-00-00...",
      "work_types": "",
      "driving_task_name": "",
      "driving_task_id": "",
      "operational_restrictions": "",
      "etops_significant": "",
      "work_package_name": "Repair (RH) ENGINE ASSEMBLY, COMPLETE PW150A (PN: 3121627-01, SN: PCE-FA0951)",
      "work_package_id": "TSFN8007XCTD",
      "work_package_no": "",
      "ro": "",
      "material_availability": "N/A",
      "scraped_at": "2025-12-12 12:12:27"
    },
    {
      "ac_registration": "ET-ASA",
      "oem_model": "Q400",
      "fault_name": "APU INOP",
      "fault_id": "TSFN800F9TAM",
      "tsfn": "TSFN800F9TAM",
      "config_position": "24-31",
      "due_date": "01-NOV-2025 23:59 EAT",
      "inventory": "24-31 - MAIN 28 VDC GENERATION SYSTEM",
      "found_on_date": "03-AUG-2025 19:24 EAT",
      "found_on_flight": "",
      "severity": "TLI",
      "status": "DEFER",
      "failure_type": "",
      "fault_priority": "",
      "deferral_class": "TLI-90D",
      "deferral_reference": "49-10",
      "work_types": "",
      "driving_task_name": "APU INOP",
      "driving_task_id": "TSFN800F9TAM",
      "operational_restrictions": "",
      "etops_significant": "",
      "work_package_name": "",
      "work_package_id": "",
      "work_package_no": "",
      "ro": "",
      "material_availability": "N/A",
      "scraped_at": "2025-12-12 12:12:27"
    },
    {
      "ac_registration": "ET-ASA",
      "oem_model": "Q400",
      "fault_name": "APU INOP",
      "fault_id": "TSFN800FAFK9",
      "tsfn": "TSFN800FAFK9",
      "config_position": "49",
      "due_date": "04-DEC-2025 23:59 EAT",
      "inventory": "49 - AUXILIARY POWER UNIT",
      "found_on_date": "06-AUG-2025 09:00 EAT",
      "found_on_flight": "ET165",
      "severity": "MINR-WD",
      "status": "DEFER",
      "failure_type": "",
      "fault_priority": "",
      "deferral_class": "MEL D",
      "deferral_reference": "49-00-1",
      "work_types": "",
      "driving_task_name": "APU INOP",
      "driving_task_id": "TSFN800FAFK9",
      "operational_restrictions": "",
      "etops_significant": "",
      "work_package_name": "",
      "work_package_id": "",
      "work_package_no": "",
      "ro": "",
      "material_availability": "N/A",
      "scraped_at": "2025-12-12 12:12:27"
    },
    {
      "ac_registration": "ET-ASA",
      "oem_model": "Q400",
      "fault_name": "ET-ASA RH ESN PCE-FA0706 -------- ENGINE LP VANE SEGMENTS RE-INSPECTION WITHIN 600FH",
      "fault_id": "TSFN800FHLG7",
      "tsfn": "TSFN800FHLG7",
      "config_position": "72-00",
      "due_date": "134.63 HOUR26-DEC-2025 23:59 EAT",
      "inventory": "72-00 - PW150A ENGINE",
      "found_on_date": "07-SEP-2025 04:22 EAT",
      "found_on_flight": "",
      "severity": "TLI",
      "status": "DEFER",
      "failure_type": "",
      "fault_priority": "",
      "deferral_class": "TLI-ENG",
      "deferral_reference": "AMM TASK 72-50-00-280-801",
      "work_types": "",
      "driving_task_name": "",
      "driving_task_id": "",
      "operational_restrictions": "",
      "etops_significant": "",
      "work_package_name": "RH BSI (@ LINE).",
      "work_package_id": "TSFN800FMTBA",
      "work_package_no": "WO - 82391045",
      "ro": "",
      "material_availability": "N/A",
      "scraped_at": "2025-12-12 12:12:27"
    },
    {
      "ac_registration": "ET-ASA",
      "oem_model": "Q400",
      "fault_name": "# 1 EMERGENCY-LIGHT POWER-SUPPLY UNITS CAN'T WORKING.",
      "fault_id": "TSFN800B23F7",
      "tsfn": "TSFN800B23F7",
      "config_position": "33-51",
      "due_date": "",
      "inventory": "33-51 - EMERGENCY LIGHT SYSTEM",
      "found_on_date": "28-JUN-2023 22:41 EAT",
      "found_on_flight": "",
      "severity": "MINR-WND",
      "status": "DEFER",
      "failure_type": "",
      "fault_priority": "",
      "deferral_class": "",
      "deferral_reference": "",
      "work_types": "",
      "driving_task_name": "",
      "driving_task_id": "",
      "operational_restrictions": "",
      "etops_significant": "",
      "work_package_name": "",
      "work_package_id": "",
      "work_package_no": "",
      "ro": "",
      "material_availability": "N/A",
      "scraped_at": "2025-12-12 12:12:27"
    },
    {
      "ac_registration": "ET-ASA",
      "oem_model": "Q400",
      "fault_name": "ADDITIONAL PARTS FOR ASA AT GDQ",
      "fault_id": "TSFN800B69FK",
      "tsfn": "TSFN800B69FK",
      "config_position": "61",
      "due_date": "",
      "inventory": "61 - PROPELLERS",
      "found_on_date": "24-JUL-2023 15:17 EAT",
      "found_on_flight": "ET125",
      "severity": "UNKNOWN",
      "status": "OPEN",
      "failure_type": "",
      "fault_priority": "",
      "deferral_class": "",
      "deferral_reference": "",
      "work_types": "",
      "driving_task_name": "",
      "driving_task_id": "",
      "operational_restrictions": "",
      "etops_significant": "",
      "work_package_name": "",
      "work_package_id": "",
      "work_package_no": "",
      "ro": "",
      "material_availability": "OPEN",
      "scraped_at": "2025-12-12 12:12:27"
    },
    {
      "ac_registration": "ET-ASA",
      "oem_model": "Q400",
      "fault_name": "BOTH LH AND RH FWDB WING TO FUSELAGE EROSSION TAPE PILLED OFF.",
      "fault_id": "TSFN8007ZF0K",
      "tsfn": "TSFN8007ZF0K",
      "config_position": "06",
      "due_date": "",
      "inventory": "06 - DIMENSIONS & AREAS",
      "found_on_date": "19-JUL-2021 15:41 EAT",
      "found_on_flight": "",
      "severity": "MINR-WND",
      "status": "DEFER",
      "failure_type": "",
      "fault_priority": "",
      "deferral_class": "",
      "deferral_reference": "",
      "work_types": "",
      "driving_task_name": "",
      "driving_task_id": "",
      "operational_restrictions": "",
      "etops_significant": "",
      "work_package_name": "",
      "work_package_id": "",
      "work_package_no": "",
      "ro": "",
      "material_availability": "OPEN",
      "scraped_at": "2025-12-12 12:12:27"
    },
    {
      "ac_registration": "ET-ASA",
      "oem_model": "Q400",
      "fault_name": "FAULT CREATED FOR INVENTORY CORRECTION",
      "fault_id": "TSFN800D1QRB",
      "tsfn": "TSFN800D1QRB",
      "config_position": "APS1000 APU->49-20-01-01-150",
      "due_date": "",
      "inventory": "FUEL CONTROL ASSEMBLY (PN: 4503139C, SN: 01-10-03)",
      "found_on_date": "24-JUL-2024 03:21 EAT",
      "found_on_flight": "",
      "severity": "UNKNOWN",
      "status": "NFF",
      "failure_type": "",
      "fault_priority": "",
      "deferral_class": "",
      "deferral_reference": "",
      "work_types": "",
      "driving_task_name": "",
      "driving_task_id": "",
      "operational_restrictions": "",
      "etops_significant": "",
      "work_package_name": "Repair FUEL CONTROL ASSEMBLY (PN: 4503139C, SN: 01-10-03)",
      "work_package_id": "TSFN800D1QRC",
      "work_package_no": "",
      "ro": "",
      "material_availability": "N/A",
      "scraped_at": "2025-12-12 12:12:27"
    },
    {
      "ac_registration": "ET-ASA",
      "oem_model": "Q400",
      "fault_name": "FLIGHT DECK DOOR CONTROLLER REMOTE ACCESS PANEL ROBBED FOR ET-AVA",
      "fault_id": "TSFN800B32J5",
      "tsfn": "TSFN800B32J5",
      "config_position": "52",
      "due_date": "",
      "inventory": "52 - DOORS",
      "found_on_date": "05-JUL-2023 00:17 EAT",
      "found_on_flight": "ET267",
      "severity": "MINR-WND",
      "status": "DEFER",
      "failure_type": "",
      "fault_priority": "",
      "deferral_class": "",
      "deferral_reference": "",
      "work_types": "",
      "driving_task_name": "",
      "driving_task_id": "",
      "operational_restrictions": "",
      "etops_significant": "",
      "work_package_name": "",
      "work_package_id": "",
      "work_package_no": "",
      "ro": "",
      "material_availability": "N/A",
      "scraped_at": "2025-12-12 12:12:27"
    },
    {
      "ac_registration": "ET-ASA",
      "oem_model": "Q400",
      "fault_name": "FOR INVENTORY CORRECTION",
      "fault_id": "TSFN800DJFFM",
      "tsfn": "TSFN800DJFFM",
      "config_position": "32-61",
      "due_date": "",
      "inventory": "32-61 - PROXIMITY SENSOR SYSTEM",
      "found_on_date": "25-OCT-2024 03:52 EAT",
      "found_on_flight": "ET150",
      "severity": "UNKNOWN",
      "status": "OPEN",
      "failure_type": "",
      "fault_priority": "",
      "deferral_class": "",
      "deferral_reference": "",
      "work_types": "",
      "driving_task_name": "",
      "driving_task_id": "",
      "operational_restrictions": "",
      "etops_significant": "",
      "work_package_name": "",
      "work_package_id": "",
      "work_package_no": "",
      "ro": "",
      "material_availability": "N/A",
      "scraped_at": "2025-12-12 12:12:27"
    },
    {
      "ac_registration": "ET-ASA",
      "oem_model": "Q400",
      "fault_name": "L/H ENGINE AFT EXHAUST JET PIPE MOUNT FOUND DETACHED.",
      "fault_id": "TSFN800801VU",
      "tsfn": "TSFN800801VU",
      "config_position": "78-10-01-01-005",
      "due_date": "",
      "inventory": "PIPE ASSY (PN: 87804005-009, SN: ET14964)",
      "found_on_date": "20-JUL-2021 15:35 EAT",
      "found_on_flight": "",
      "severity": "UNKNOWN",
      "status": "NFF",
      "failure_type": "",
      "fault_priority": "",
      "deferral_class": "",
      "deferral_reference": "",
      "work_types": "",
      "driving_task_name": "",
      "driving_task_id": "",
      "operational_restrictions": "",
      "etops_significant": "",
      "work_package_name": "Repair PIPE ASSY (PN: 87804005-009, SN: X X X)",
      "work_package_id": "TSFN800801VV",
      "work_package_no": "",
      "ro": "",
      "material_availability": "N/A",
      "scraped_at": "2025-12-12 12:12:27"
    },
    {
      "ac_registration": "ET-ASA",
      "oem_model": "Q400",
      "fault_name": "L/H ENGINE AFT UPPER NACELLE SEAL FOUND DAMAGED.",
      "fault_id": "TSFN8007ZK49",
      "tsfn": "TSFN8007ZK49",
      "config_position": "54-31",
      "due_date": "",
      "inventory": "54-31 - AFT NACELLE",
      "found_on_date": "20-JUL-2021 15:40 EAT",
      "found_on_flight": "",
      "severity": "MINR-WND",
      "status": "DEFER",
      "failure_type": "",
      "fault_priority": "",
      "deferral_class": "",
      "deferral_reference": "",
      "work_types": "",
      "driving_task_name": "",
      "driving_task_id": "",
      "operational_restrictions": "",
      "etops_significant": "",
      "work_package_name": "",
      "work_package_id": "",
      "work_package_no": "",
      "ro": "",
      "material_availability": "N/A",
      "scraped_at": "2025-12-12 12:12:27"
    },
    {
      "ac_registration": "ET-ASA",
      "oem_model": "Q400",
      "fault_name": "PART INVENTORY",
      "fault_id": "TSFN800D6TAX",
      "tsfn": "TSFN800D6TAX",
      "config_position": "PROP150A (LT) ->61-10",
      "due_date": "",
      "inventory": "61-10 - PROPELER",
      "found_on_date": "21-AUG-2024 09:30 EAT",
      "found_on_flight": "",
      "severity": "MINR-WND",
      "status": "DEFER",
      "failure_type": "",
      "fault_priority": "",
      "deferral_class": "",
      "deferral_reference": "",
      "work_types": "",
      "driving_task_name": "",
      "driving_task_id": "",
      "operational_restrictions": "",
      "etops_significant": "",
      "work_package_name": "",
      "work_package_id": "",
      "work_package_no": "",
      "ro": "",
      "material_availability": "N/A",
      "scraped_at": "2025-12-12 12:12:27"
    },
    {
      "ac_registration": "ET-ASA",
      "oem_model": "Q400",
      "fault_name": "POWERPLANT MSG ON ED WITH FC 238",
      "fault_id": "TSFN800B69D3",
      "tsfn": "TSFN800B69D3",
      "config_position": "PROP150A (RT) ->UNTRKD (1.1)",
      "due_date": "",
      "inventory": "UNTRKD - UNTRACKED PARTS (SER AND BATCH)",
      "found_on_date": "24-JUL-2023 15:01 EAT",
      "found_on_flight": "ET125",
      "severity": "MINR-WND",
      "status": "DEFER",
      "failure_type": "",
      "fault_priority": "",
      "deferral_class": "",
      "deferral_reference": "",
      "work_types": "",
      "driving_task_name": "",
      "driving_task_id": "",
      "operational_restrictions": "",
      "etops_significant": "",
      "work_package_name": "",
      "work_package_id": "",
      "work_package_no": "",
      "ro": "",
      "material_availability": "N/A",
      "scraped_at": "2025-12-12 12:12:27"
    },
    {
      "ac_registration": "ET-ASA",
      "oem_model": "Q400",
      "fault_name": "R/H ENGINE AFT UPPER NACELLE SEAL FOUND DAMAGED.",
      "fault_id": "TSFN8007ZK86",
      "tsfn": "TSFN8007ZK86",
      "config_position": "54-31",
      "due_date": "",
      "inventory": "54-31 - AFT NACELLE",
      "found_on_date": "20-JUL-2021 16:25 EAT",
      "found_on_flight": "",
      "severity": "MINR-WND",
      "status": "DEFER",
      "failure_type": "",
      "fault_priority": "",
      "deferral_class": "",
      "deferral_reference": "",
      "work_types": "",
      "driving_task_name": "",
      "driving_task_id": "",
      "operational_restrictions": "",
      "etops_significant": "",
      "work_package_name": "",
      "work_package_id": "",
      "work_package_no": "",
      "ro": "",
      "material_availability": "N/A",
      "scraped_at": "2025-12-12 12:12:27"
    },
    {
      "ac_registration": "ET-ASA",
      "oem_model": "Q400",
      "fault_name": "RH MLG FWD DOOR",
      "fault_id": "TSFN80073HTE",
      "tsfn": "TSFN80073HTE",
      "config_position": "32",
      "due_date": "",
      "inventory": "32 - LANDING GEAR",
      "found_on_date": "03-DEC-2020 00:50 EAT",
      "found_on_flight": "",
      "severity": "MINR-WND",
      "status": "DEFER",
      "failure_type": "",
      "fault_priority": "",
      "deferral_class": "",
      "deferral_reference": "",
      "work_types": "",
      "driving_task_name": "",
      "driving_task_id": "",
      "operational_restrictions": "",
      "etops_significant": "",
      "work_package_name": "",
      "work_package_id": "",
      "work_package_no": "",
      "ro": "",
      "material_availability": "N/A",
      "scraped_at": "2025-12-12 12:12:27"
    },
    {
      "ac_registration": "ET-ASA",
      "oem_model": "Q400",
      "fault_name": "SPINNER HAS NO PPT",
      "fault_id": "TSFN800G2S2H",
      "tsfn": "TSFN800G2S2H",
      "config_position": "PROP150A (RT)",
      "due_date": "",
      "inventory": "(RT) PROPELLER ASSY (PN: 697070003, SN: DAP1342)",
      "found_on_date": "03-DEC-2025 16:02 EAT",
      "found_on_flight": "",
      "severity": "UNKNOWN",
      "status": "OPEN",
      "failure_type": "",
      "fault_priority": "",
      "deferral_class": "",
      "deferral_reference": "",
      "work_types": "",
      "driving_task_name": "",
      "driving_task_id": "",
      "operational_restrictions": "",
      "etops_significant": "",
      "work_package_name": "SPINNER HAS NO PPT",
      "work_package_id": "TSFN800G2S2J",
      "work_package_no": "WO - 85125558",
      "ro": "",
      "material_availability": "N/A",
      "scraped_at": "2025-12-12 12:12:27"
    },
    {
      "ac_registration": "ET-ASA",
      "oem_model": "Q400",
      "fault_name": "STBY,MAIN AND AUX BATTERYS ARE DRAINED.",
      "fault_id": "TSFN800A2RYQ",
      "tsfn": "TSFN800A2RYQ",
      "config_position": "24-32",
      "due_date": "",
      "inventory": "24-32 - BATTERY SYSTEM",
      "found_on_date": "27-NOV-2022 21:55 EAT",
      "found_on_flight": "",
      "severity": "MINR-WND",
      "status": "DEFER",
      "failure_type": "",
      "fault_priority": "",
      "deferral_class": "",
      "deferral_reference": "",
      "work_types": "",
      "driving_task_name": "",
      "driving_task_id": "",
      "operational_restrictions": "",
      "etops_significant": "",
      "work_package_name": "",
      "work_package_id": "",
      "work_package_no": "",
      "ro": "",
      "material_availability": "N/A",
      "scraped_at": "2025-12-12 12:12:27"
    },
    {
      "ac_registration": "ET-ASA",
      "oem_model": "Q400",
      "fault_name": "THE GRAVEL PROTECTOR AT NOSE LOWER FUSELAGE ARREA HA PILLED OFF.",
      "fault_id": "TSFN80043SNW",
      "tsfn": "TSFN80043SNW",
      "config_position": "53",
      "due_date": "",
      "inventory": "53 - FUSELAGE",
      "found_on_date": "23-MAY-2018 22:58 EAT",
      "found_on_flight": "ET375",
      "severity": "UNKNOWN",
      "status": "NFF",
      "failure_type": "",
      "fault_priority": "",
      "deferral_class": "",
      "deferral_reference": "",
      "work_types": "",
      "driving_task_name": "",
      "driving_task_id": "",
      "operational_restrictions": "",
      "etops_significant": "",
      "work_package_name": "#2 ENGINE CHANGE",
      "work_package_id": "TSFN8002JP9A",
      "work_package_no": "WO - 14714671",
      "ro": "",
      "material_availability": "N/A",
      "scraped_at": "2025-12-12 12:12:27"
    },
    {
      "ac_registration": "ET-ASA",
      "oem_model": "Q400",
      "fault_name": "WHEN PERFORMING ELEVATOR PCU'S FREE PLAY CHECK, THE RIGHT HAND ELEVATOR HAS FAILED THE CHECK",
      "fault_id": "TSFN8007MJV1",
      "tsfn": "TSFN8007MJV1",
      "config_position": "27-31",
      "due_date": "",
      "inventory": "27-31 - ELEVATOR SYSTEM",
      "found_on_date": "21-APR-2021 16:09 EAT",
      "found_on_flight": "ET135",
      "severity": "UNKNOWN",
      "status": "OPEN",
      "failure_type": "",
      "fault_priority": "",
      "deferral_class": "",
      "deferral_reference": "",
      "work_types": "",
      "driving_task_name": "",
      "driving_task_id": "",
      "operational_restrictions": "",
      "etops_significant": "",
      "work_package_name": "",
      "work_package_id": "",
      "work_package_no": "",
      "ro": "",
      "material_availability": "N/A",
      "scraped_at": "2025-12-12 12:12:27"
    }
  ],
  "scraped_at": "2025-12-12T12:12:27.682645"
}